Workbook

Sheet aida
A1: Anno | B1: 31/12/2024 | C1: 31/12/2023 | D1: 31/12/2022 | E1: 31/12/2021 | F1: 31/12/2020 | G1: 31/12/2019 | H1: 31/12/2018 | I1: 31/12/2017
A2: A. CREDITI VERSO SOCI | B2: 0 | C2: 0 | D2: 0 | E2: 0 | F2: 0 | G2: 0 | H2: 0 | I2: 0
A3: Quota di capitale richiamata | B3: 0 | C3: 0 | D3: 0 | E3: 0 | F3: 0 | G3: 0 | H3: 0 | I3: 0
A4: B. TOTALE IMMOBILIZZAZIONI sep.ind. Di quelle conc. In loc. Finanz. | B4: 8842950 | C4: 9182852 | D4: 9614947 | E4: 9565702 | F4: 7073181 | G4: 2616289 | H4: 1201123 | I4: 908499
A5: B.I. TOTALE IMMOB. IMMATERIALI | B5: 89523 | C5: 106380 | D5: 139717 | E5: 76490 | F5: 33453 | G5: 7543 | H5: 0 | I5: 1977
A6: B.I.1. Costi impianto e ampl. | B6: 0 | C6: 0 | D6: 0 | E6: 0 | F6: 0 | G6: 0 | H6: 0 | I6: 0
A7: B.I.2. Costi ricerca e pubb. | B7: 0 | C7: 0 | D7: 0 | E7: 0 | F7: 0 | G7: 0 | H7: 0 | I7: 0
A8: B.I.3. Diritti brevetto ind. | B8: 64590 | C8: 97381 | D8: 130172 | E8: 3968 | F8: 4960 | G8: 0 | H8: 0 | I8: 0
A9: B.I.4. Concessioni, licenze | B9: 8453 | C9: 8999 | D9: 9545 | E9: 0 | F9: 0 | G9: 0 | H9: 0 | I9: 0
A10: B.I.5. Avviamento/Differenza di consolidamento | B10: 0 | C10: 0 | D10: 0 | E10: 0 | F10: 0 | G10: 0 | H10: 0 | I10: 0
A11: di cui: Avviamento | B11: 0 | C11: 0 | D11: 0 | E11: 0 | F11: 0 | G11: 0 | H11: 0 | I11: 0
A12: B.I.6. Imm. in corso | B12: 0 | C12: 0 | D12: 0 | E12: 67622 | F12: 28493 | G12: 7543 | H12: 0 | I12: 0
A13: B.I.7. Altre immobiliz. Immateriali | B13: 16480 | C13: 0 | D13: 0 | E13: 4900 | F13: 0 | G13: 0 | H13: 0 | I13: 1977
... A93: TOTALE ATTIVO | B93: 18790859 | C93: 20554377 | D93: 20723060 | E93: 18204611 | F93: 14795011 | G93: 9311398 | H93: 6455031 | I93: 6151737
A94: Passivo
A95: PATRIMONIO NETTO
A96: A. TOTALE PATRIMONIO NETTO | B96: 5757287 | C96: 5227552 | D96: 4660887 | E96: 4082303 | F96: 3206001 | G96: 2384718 | H96: 1733081 | I96: 1062658
A97: A.I. Capitale sociale | B97: 140000 | C97: 140000 | D97: 140000 | E97: 140000 | F97: 140000 | G97: 140000 | H97: 140000 | I97: 140000
A98: di cui: Versamenti soci in c/capitale | B98: 0 | C98: 0 | D98: 0 | E98: 0 | F98: 0 | G98: 0 | H98: 0 | I98: 0
A99: di cui: Versamenti in c/futuro aumento di capitale | B99: 0 | C99: 0 | D99: 0 | E99: 0 | F99: 0 | G99: 0 | H99: 0 | I99: 0
A100: di cui: Versamenti in c/capitale | B100: 0 | C100: 0 | D100: 0 | E100: 0 | F100: 0 | G100: 0 | H100: 0 | I100: 0
A101: di cui: Versamenti a copertura perdite | B101: 0 | C101: 0 | D101: 0 | E101: 0 | F101: 0 | G101: 0 | H101: 0 | I101: 0
A102: A.II. Riserva da sovrapprezzo | B102: 0 | C102: 0 | D102: 0 | E102: 0 | F102: 0 | G102: 0 | H102: 0 | I102: 0
A103: A.III. Riserva di rivalutazione | B103: 0 | C103: 0 | D103: 0 | E103: 0 | F103: 0 | G103: 0 | H103: 0 | I103: 0
A104: A.IV. Riserva legale | B104: 28000 | C104: 28000 | D104: 28000 | E104: 28000 | F104: 28000 | G104: 28000 | H104: 18237 | I104: 0
A105: A.V. Riserva statutaria | B105: 0 | C105: 0 | D105: 0 | E105: 0 | F105: 0 | G105: 0 | H105: 0 | I105: 0
A106: Riserva azioni proprie | B106: 0 | C106: 0 | D106: 0 | E106: 0 | F106: 0 | G106: 0 | H106: 0 | I106: 0
A107: A.VI. Altre riserve | B107: 4689554 | C107: 4492885 | D107: 3814306 | E107: 2953000 | F107: 2116719 | G107: 1465082 | H107: 904419 | I107: -1
... A126: C. TRATTAMENTO DI FINE RAPPORTO | B126: 191675 | C126: 179286 | D126: 189098 | E126: 197380 | F126: 174392 | G126: 206556 | H126: 187238 | I126: 173667
A127: Debiti
A128: D. TOTALE DEBITI | B128: 11906052 | C128: 13914499 | D128: 14618344 | E128: 13815442 | F128: 11347602 | G128: 6671454 | H128: 4468030 | I128: 4868877
A129: D.1. Obblig.ni entro | B129: 0 | C129: 0 | D129: 0 | E129: 0 | F129: 0 | G129: 0 | H129: 0 | I129: 0
A130: D.1. Obblig.ni oltre | B130: 0 | C130: 0 | D130: 0 | E130: 0 | F130: 0 | G130: 0 | H130: 0 | I130: 0
A131: D.2. Obblig.ni convert. entro | B131: 0 | C131: 0 | D131: 0 | E131: 0 | F131: 0 | G131: 0 | H131: 0 | I131: 0
A132: D.2. Obblig.ni convert. oltre. | B132: 0 | C132: 0 | D132: 0 | E132: 0 | F132: 0 | G132: 0 | H132: 0 | I132: 0
A133: D.3. Soci per Finanziamenti entro | B133: 0 | C133: 0 | D133: 0 | E133: 0 | F133: 0 | G133: 0 | H133: 0 | I133: 0
A134: D.3. Soci per Finanziamenti oltre | B134: 0 | C134: 0 | D134: 0 | E134: 0 | F134: 0 | G134: 0 | H134: 0 | I134: 0
A135: D.4. Banche entro l'esercizio | B135: 3395294 | C135: 3987523 | D135: 4519420 | E135: 3495062 | F135: 2923930 | G135: 3390744 | H135: 1825267 | I135: 1954310
A136: D.4. Banche oltre l'esercizio | B136: 5110204 | C136: 6691873 | D136: 6691933 | E136: 7333471 | F136: 6304053 | G136: 588287 | H136: 808395 | I136: 952264
A137: D.5. Altri finanziatori entro | B137: 435 | C137: 435 | D137: 435 | E137: 435 | F137: 310 | G137: 0 | H137: 120 | I137: 0
A138: D.5. Altri finanziatori oltre | B138: 0 | C138: 0 | D138: 25580 | E138: 38724 | F138: 0 | G138: 0 | H138: 0 | I138: 0
A139: D.6. Acconti entro | B139: 0 | C139: 0 | D139: 0 | E139: 0 | F139: 0 | G139: 73 | H139: 73 | I139: 0
... A166: TOTALE CONTI D'ORDINE | B166: 0 | C166: 0 | D166: 0 | E166: 0 | F166: 0 | G166: 0 | H166: 0 | I166: 0
A167: Conto economico
A168: A. TOT. VAL. DELLA PRODUZIONE | B168: 21175083 | C168: 21333756 | D168: 20175039 | E168: 15943683 | F168: 13994258 | G168: 14096980 | H168: 11927860 | I168: 9845054
A169: A.1. Ricavi vendite e prestazioni | B169: 21463379 | C169: 20988520 | D169: 17588847 | E169: 15559839 | F169: 14316092 | G169: 13473198 | H169: 11493812 | I169: 9891413
A170: A.2. Var. rimanenze prodotti | B170: -573471 | C170: -74468 | D170: 2163754 | E170: 288102 | F170: -377792 | G170: 494422 | H170: 386643 | I170: -75281
A171: A.3. Variazione lavori | B171: 0 | C171: 0 | D171: 0 | E171: 0 | F171: 0 | G171: 0 | H171: 0 | I171: 0
A172: A.2. + A.3. Totale Variazioni | B172: -573471 | C172: -74468 | D172: 2163754 | E172: 288102 | F172: -377792 | G172: 494422 | H172: 386643 | I172: -75281
A173: A.4. Incrementi di immob. | B173: 0 | C173: 0 | D173: 0 | E173: 0 | F173: 0 | G173: 0 | H173: 0 | I173: 0
A174: A.5. Altri ricavi | B174: 285175 | C174: 419704 | D174: 422438 | E174: 95742 | F174: 55958 | G174: 129360 | H174: 47405 | I174: 28922
A175: Contributi in conto esercizio | B175: 97559 | C175: 265833 | D175: 189996 | E175: 17223 | F175: 35171 | G175: 52406 | H175: 21783 | I175: 2994
A176: B. COSTI DELLA PRODUZIONE | B176: 19586234 | C176: 20216429 | D176: 19211064 | E176: 14532426 | F176: 12642532 | G176: 13027353 | H176: 10874910 | I176: 9209207
A177: B.6. Materie prime e consumo | B177: 14699595 | C177: 14953922 | D177: 13825249 | E177: 10511247 | F177: 9060210 | G177: 9472095 | H177: 7620373 | I177: 6509298
A178: B.7. Servizi | B178: 2422226 | C178: 2512120 | D178: 2928006 | E178: 2010409 | F178: 1917407 | G178: 1966664 | H178: 1696231 | I178: 1342031
A179: B.8. Godimento beni di terzi | B179: 117380 | C179: 75105 | D179: 85474 | E179: 78590 | F179: 73502 | G179: 66140 | H179: 53268 | I179: 64128
... A246: UTILE/PERDITA DI ESERCIZIO di pert. di TERZI | B246: 0 | C246: 0 | D246: 0 | E246: 0 | F246: 0 | G246: 0 | H246: 0 | I246: 0
A247: BOME' S.P.A.
A248: 00369120225

Sheet case
A1: SP attivo | B1: =aida!B1 -> 31/12/2024 | C1: =aida!C1 -> 31/12/2023 | D1: =aida!D1 -> 31/12/2022 | E1: =aida!E1 -> 31/12/2021 | F1: =aida!F1 -> 31/12/2020 | G1: =aida!G1 -> 31/12/2019 | H1: =aida!H1 -> 31/12/2018 | I1: =aida!I1 -> 31/12/2017 | K1: Segno | L1: Riclassificazione
A2: =aida!A2 -> A. CREDITI VERSO SOCI | B2: =$K2*aida!B2 -> 0 | C2: =$K2*aida!C2 -> 0 | D2: =$K2*aida!D2 -> 0 | E2: =$K2*aida!E2 -> 0 | F2: =$K2*aida!F2 -> 0 | G2: =$K2*aida!G2 -> 0 | H2: =$K2*aida!H2 -> 0 | I2: =$K2*aida!I2 -> 0 | K2: -1 | L2: Finanziamenti netti vs soci e controllanti
A3: =aida!A3 -> Quota di capitale richiamata | B3: =$K3*aida!B3 -> 0 | C3: =$K3*aida!C3 -> 0 | D3: =$K3*aida!D3 -> 0 | E3: =$K3*aida!E3 -> 0 | F3: =$K3*aida!F3 -> 0 | G3: =$K3*aida!G3 -> 0 | H3: =$K3*aida!H3 -> 0 | I3: =$K3*aida!I3 -> 0 | K3: 1
A5: =aida!A4 -> B. TOTALE IMMOBILIZZAZIONI sep.ind. Di quelle conc. In loc. Finanz. | B5: =$K5*aida!B4 -> 8842950 | C5: =$K5*aida!C4 -> 9182852 | D5: =$K5*aida!D4 -> 9614947 | E5: =$K5*aida!E4 -> 9565702 | F5: =$K5*aida!F4 -> 7073181 | G5: =$K5*aida!G4 -> 2616289 | H5: =$K5*aida!H4 -> 1201123 | I5: =$K5*aida!I4 -> 908499 | K5: 1
A6: =aida!A5 -> B.I. TOTALE IMMOB. IMMATERIALI | B6: =$K6*aida!B5 -> 89523 | C6: =$K6*aida!C5 -> 106380 | D6: =$K6*aida!D5 -> 139717 | E6: =$K6*aida!E5 -> 76490 | F6: =$K6*aida!F5 -> 33453 | G6: =$K6*aida!G5 -> 7543 | H6: =$K6*aida!H5 -> 0 | I6: =$K6*aida!I5 -> 1977 | K6: 1 | L6: Immobilizzazioni immateriali nette
A7: =aida!A6 -> B.I.1. Costi impianto e ampl. | B7: =$K7*aida!B6 -> 0 | C7: =$K7*aida!C6 -> 0 | D7: =$K7*aida!D6 -> 0 | E7: =$K7*aida!E6 -> 0 | F7: =$K7*aida!F6 -> 0 | G7: =$K7*aida!G6 -> 0 | H7: =$K7*aida!H6 -> 0 | I7: =$K7*aida!I6 -> 0 | K7: 1
A8: =aida!A7 -> B.I.2. Costi ricerca e pubb. | B8: =$K8*aida!B7 -> 0 | C8: =$K8*aida!C7 -> 0 | D8: =$K8*aida!D7 -> 0 | E8: =$K8*aida!E7 -> 0 | F8: =$K8*aida!F7 -> 0 | G8: =$K8*aida!G7 -> 0 | H8: =$K8*aida!H7 -> 0 | I8: =$K8*aida!I7 -> 0 | K8: 1
A9: =aida!A8 -> B.I.3. Diritti brevetto ind. | B9: =$K9*aida!B8 -> 64590 | C9: =$K9*aida!C8 -> 97381 | D9: =$K9*aida!D8 -> 130172 | E9: =$K9*aida!E8 -> 3968 | F9: =$K9*aida!F8 -> 4960 | G9: =$K9*aida!G8 -> 0 | H9: =$K9*aida!H8 -> 0 | I9: =$K9*aida!I8 -> 0 | K9: 1
A10: =aida!A9 -> B.I.4. Concessioni, licenze | B10: =$K10*aida!B9 -> 8453 | C10: =$K10*aida!C9 -> 8999 | D10: =$K10*aida!D9 -> 9545 | E10: =$K10*aida!E9 -> 0 | F10: =$K10*aida!F9 -> 0 | G10: =$K10*aida!G9 -> 0 | H10: =$K10*aida!H9 -> 0 | I10: =$K10*aida!I9 -> 0 | K10: 1
A11: =aida!A10 -> B.I.5. Avviamento/Differenza di consolidamento | B11: =$K11*aida!B10 -> 0 | C11: =$K11*aida!C10 -> 0 | D11: =$K11*aida!D10 -> 0 | E11: =$K11*aida!E10 -> 0 | F11: =$K11*aida!F10 -> 0 | G11: =$K11*aida!G10 -> 0 | H11: =$K11*aida!H10 -> 0 | I11: =$K11*aida!I10 -> 0 | K11: 1
A12: =aida!A11 -> di cui: Avviamento | B12: =$K12*aida!B11 -> 0 | C12: =$K12*aida!C11 -> 0 | D12: =$K12*aida!D11 -> 0 | E12: =$K12*aida!E11 -> 0 | F12: =$K12*aida!F11 -> 0 | G12: =$K12*aida!G11 -> 0 | H12: =$K12*aida!H11 -> 0 | I12: =$K12*aida!I11 -> 0 | K12: 1
A13: =aida!A12 -> B.I.6. Imm. in corso | B13: =$K13*aida!B12 -> 0 | C13: =$K13*aida!C12 -> 0 | D13: =$K13*aida!D12 -> 0 | E13: =$K13*aida!E12 -> 67622 | F13: =$K13*aida!F12 -> 28493 | G13: =$K13*aida!G12 -> 7543 | H13: =$K13*aida!H12 -> 0 | I13: =$K13*aida!I12 -> 0 | K13: 1
A14: =aida!A13 -> B.I.7. Altre immobiliz. Immateriali | B14: =$K14*aida!B13 -> 16480 | C14: =$K14*aida!C13 -> 0 | D14: =$K14*aida!D13 -> 0 | E14: =$K14*aida!E13 -> 4900 | F14: =$K14*aida!F13 -> 0 | G14: =$K14*aida!G13 -> 0 | H14: =$K14*aida!H13 -> 0 | I14: =$K14*aida!I13 -> 1977 | K14: 1
A15: =aida!A14 -> Fondo amm.to Immob. Immateriali | B15: =$K15*aida!B14 -> 0 | C15: =$K15*aida!C14 -> 0 | D15: =$K15*aida!D14 -> 0 | E15: =$K15*aida!E14 -> 0 | F15: =$K15*aida!F14 -> 0 | G15: =$K15*aida!G14 -> 0 | H15: =$K15*aida!H14 -> 0 | I15: =$K15*aida!I14 -> 0 | K15: 1
A16: =aida!A15 -> B.II. TOTALE IMMOB. MATERIALI | B16: =$K16*aida!B15 -> 8694725 | C16: =$K16*aida!C15 -> 9017770 | D16: =$K16*aida!D15 -> 9416528 | E16: =$K16*aida!E15 -> 9430510 | F16: =$K16*aida!F15 -> 7025024 | G16: =$K16*aida!G15 -> 2594042 | H16: =$K16*aida!H15 -> 1186419 | I16: =$K16*aida!I15 -> 891818 | K16: 1 | L16: Immobilizzazioni materiali nette
A17: =aida!A16 -> di cui: Beni materiali concessi in locazione finanziaria | B17: =$K17*aida!B16 -> 0 | C17: =$K17*aida!C16 -> 0 | D17: =$K17*aida!D16 -> 0 | E17: =$K17*aida!E16 -> 0 | F17: =$K17*aida!F16 -> 0 | G17: =$K17*aida!G16 -> 0 | H17: =$K17*aida!H16 -> 0 | I17: =$K17*aida!I16 -> 0 | K17: 1
A18: =aida!A17 -> B.II.1. Terreni e fabbricati | B18: =$K18*aida!B17 -> 6069102 | C18: =$K18*aida!C17 -> 6328571 | D18: =$K18*aida!D17 -> 6543383 | E18: =$K18*aida!E17 -> 6374984 | F18: =$K18*aida!F17 -> 396319 | G18: =$K18*aida!G17 -> 412628 | H18: =$K18*aida!H17 -> 418736 | I18: =$K18*aida!I17 -> 324645 | K18: 1
A19: =aida!A18 -> B.II.2. Impianti | B19: =$K19*aida!B18 -> 1774810 | C19: =$K19*aida!C18 -> 2137598 | D19: =$K19*aida!D18 -> 2352511 | E19: =$K19*aida!E18 -> 2232169 | F19: =$K19*aida!F18 -> 1801043 | G19: =$K19*aida!G18 -> 258024 | H19: =$K19*aida!H18 -> 302043 | I19: =$K19*aida!I18 -> 336024 | K19: 1
A20: =aida!A19 -> B.II.3. Attrez. industriali | B20: =$K20*aida!B19 -> 197170 | C20: =$K20*aida!C19 -> 187192 | D20: =$K20*aida!D19 -> 184756 | E20: =$K20*aida!E19 -> 168289 | F20: =$K20*aida!F19 -> 141111 | G20: =$K20*aida!G19 -> 110856 | H20: =$K20*aida!H19 -> 130147 | I20: =$K20*aida!I19 -> 133231 | K20: 1
A21: =aida!A20 -> B.II.4. Altri beni | B21: =$K21*aida!B20 -> 177873 | C21: =$K21*aida!C20 -> 244518 | D21: =$K21*aida!D20 -> 312178 | E21: =$K21*aida!E20 -> 236539 | F21: =$K21*aida!F20 -> 116965 | G21: =$K21*aida!G20 -> 45295 | H21: =$K21*aida!H20 -> 68843 | I21: =$K21*aida!I20 -> 97918 | K21: 1
A22: =aida!A21 -> B.II.5. Imm. in corso/acconti | B22: =$K22*aida!B21 -> 475770 | C22: =$K22*aida!C21 -> 119891 | D22: =$K22*aida!D21 -> 23700 | E22: =$K22*aida!E21 -> 418529 | F22: =$K22*aida!F21 -> 4569586 | G22: =$K22*aida!G21 -> 1767239 | H22: =$K22*aida!H21 -> 266650 | I22: =$K22*aida!I21 -> 0 | K22: 1
A23: =aida!A22 -> Fondo amm.to Immob. Materiali | B23: =$K23*aida!B22 -> 0 | C23: =$K23*aida!C22 -> 0 | D23: =$K23*aida!D22 -> 0 | E23: =$K23*aida!E22 -> 0 | F23: =$K23*aida!F22 -> 0 | G23: =$K23*aida!G22 -> 0 | H23: =$K23*aida!H22 -> 0 | I23: =$K23*aida!I22 -> 0 | K23: 1
A24: =aida!A23 -> B.III. TOTALE IMMOB. FINANZIARIE | B24: =$K24*aida!B23 -> 58702 | C24: =$K24*aida!C23 -> 58702 | D24: =$K24*aida!D23 -> 58702 | E24: =$K24*aida!E23 -> 58702 | F24: =$K24*aida!F23 -> 14704 | G24: =$K24*aida!G23 -> 14704 | H24: =$K24*aida!H23 -> 14704 | I24: =$K24*aida!I23 -> 14704 | K24: 1
A25: =aida!A24 -> di cui: esigibili entro l'esercizio successivo | B25: =$K25*aida!B24 -> 0 | C25: =$K25*aida!C24 -> 0 | D25: =$K25*aida!D24 -> 0 | E25: =$K25*aida!E24 -> 0 | F25: =$K25*aida!F24 -> 8192 | G25: =$K25*aida!G24 -> 8192 | H25: =$K25*aida!H24 -> 8192 | I25: =$K25*aida!I24 -> 0 | K25: 1
A26: =aida!A25 -> B.III.1. TOT Partecipazioni | B26: =$K26*aida!B25 -> 58702 | C26: =$K26*aida!C25 -> 58702 | D26: =$K26*aida!D25 -> 58702 | E26: =$K26*aida!E25 -> 58702 | F26: =$K26*aida!F25 -> 6512 | G26: =$K26*aida!G25 -> 6512 | H26: =$K26*aida!H25 -> 6512 | I26: =$K26*aida!I25 -> 6512 | K26: 1
A27: =aida!A26 -> B.III.1.a. Imprese controllate | B27: =$K27*aida!B26 -> 0 | C27: =$K27*aida!C26 -> 0 | D27: =$K27*aida!D26 -> 0 | E27: =$K27*aida!E26 -> 0 | F27: =$K27*aida!F26 -> 0 | G27: =$K27*aida!G26 -> 0 | H27: =$K27*aida!H26 -> 0 | I27: =$K27*aida!I26 -> 0 | K27: 1 | L27: Partecipazioni
A28: =aida!A27 -> B.III.1.b. Imprese collegate | B28: =$K28*aida!B27 -> 0 | C28: =$K28*aida!C27 -> 0 | D28: =$K28*aida!D27 -> 0 | E28: =$K28*aida!E27 -> 0 | F28: =$K28*aida!F27 -> 0 | G28: =$K28*aida!G27 -> 0 | H28: =$K28*aida!H27 -> 0 | I28: =$K28*aida!I27 -> 0 | K28: 1 | L28: Partecipazioni
A29: =aida!A28 -> B.III.1.c. Imprese controllanti | B29: =$K29*aida!B28 -> 0 | C29: =$K29*aida!C28 -> 0 | D29: =$K29*aida!D28 -> 0 | E29: =$K29*aida!E28 -> 0 | F29: =$K29*aida!F28 -> 0 | G29: =$K29*aida!G28 -> 0 | H29: =$K29*aida!H28 -> 0 | I29: =$K29*aida!I28 -> 0 | K29: 1 | L29: Azioni proprie e partecipazioni in controllanti
A30: =aida!A29 -> B.III.1.d. In imprese sottoposte al controllo delle controllanti | B30: =$K30*aida!B29 -> 0 | C30: =$K30*aida!C29 -> 0 | D30: =$K30*aida!D29 -> 0 | E30: =$K30*aida!E29 -> 0 | F30: =$K30*aida!F29 -> 0 | G30: =$K30*aida!G29 -> 0 | H30: =$K30*aida!H29 -> 0 | I30: =$K30*aida!I29 -> 0 | K30: 1 | L30: Partecipazioni
A31: =aida!A30 -> B.III.1.d.bis. Altre imprese | B31: =$K31*aida!B30 -> 58702 | C31: =$K31*aida!C30 -> 58702 | D31: =$K31*aida!D30 -> 58702 | E31: =$K31*aida!E30 -> 58702 | F31: =$K31*aida!F30 -> 6512 | G31: =$K31*aida!G30 -> 6512 | H31: =$K31*aida!H30 -> 6512 | I31: =$K31*aida!I30 -> 6512 | K31: 1 | L31: Partecipazioni
A32: =aida!A31 -> B.III.2. TOT CREDITI Imm. Fin. | B32: =$K32*aida!B31 -> 0 | C32: =$K32*aida!C31 -> 0 | D32: =$K32*aida!D31 -> 0 | E32: =$K32*aida!E31 -> 0 | F32: =$K32*aida!F31 -> 8192 | G32: =$K32*aida!G31 -> 8192 | H32: =$K32*aida!H31 -> 8192 | I32: =$K32*aida!I31 -> 8192 | K32: 1
A33: =aida!A32 -> B.III.2.a. Cred. vs Controllate entro | B33: =$K33*aida!B32 -> 0 | C33: =$K33*aida!C32 -> 0 | D33: =$K33*aida!D32 -> 0 | E33: =$K33*aida!E32 -> 0 | F33: =$K33*aida!F32 -> 0 | G33: =$K33*aida!G32 -> 0 | H33: =$K33*aida!H32 -> 0 | I33: =$K33*aida!I32 -> 0 | K33: 1 | L33: Crediti vs controllate e collegate
A34: =aida!A33 -> B.III.2.a. Cred. vs Controllate oltre | B34: =$K34*aida!B33 -> 0 | C34: =$K34*aida!C33 -> 0 | D34: =$K34*aida!D33 -> 0 | E34: =$K34*aida!E33 -> 0 | F34: =$K34*aida!F33 -> 0 | G34: =$K34*aida!G33 -> 0 | H34: =$K34*aida!H33 -> 0 | I34: =$K34*aida!I33 -> 0 | K34: 1 | L34: Crediti vs controllate e collegate
A35: =aida!A34 -> B.III.2.b. Cred. vs Collegate entro | B35: =$K35*aida!B34 -> 0 | C35: =$K35*aida!C34 -> 0 | D35: =$K35*aida!D34 -> 0 | E35: =$K35*aida!E34 -> 0 | F35: =$K35*aida!F34 -> 0 | G35: =$K35*aida!G34 -> 0 | H35: =$K35*aida!H34 -> 0 | I35: =$K35*aida!I34 -> 0 | K35: 1 | L35: Crediti vs controllate e collegate
A36: =aida!A35 -> B.III.2.b. Cred. vs Collegate oltre | B36: =$K36*aida!B35 -> 0 | C36: =$K36*aida!C35 -> 0 | D36: =$K36*aida!D35 -> 0 | E36: =$K36*aida!E35 -> 0 | F36: =$K36*aida!F35 -> 0 | G36: =$K36*aida!G35 -> 0 | H36: =$K36*aida!H35 -> 0 | I36: =$K36*aida!I35 -> 0 | K36: 1 | L36: Crediti vs controllate e collegate
A37: =aida!A36 -> B.III.2.c. Cred. vs Controllanti entro | B37: =$K37*aida!B36 -> 0 | C37: =$K37*aida!C36 -> 0 | D37: =$K37*aida!D36 -> 0 | E37: =$K37*aida!E36 -> 0 | F37: =$K37*aida!F36 -> 0 | G37: =$K37*aida!G36 -> 0 | H37: =$K37*aida!H36 -> 0 | I37: =$K37*aida!I36 -> 0 | K37: 1 | L37: Immobilizzazioni extra-operative
A38: =aida!A37 -> B.III.2.c. Cred. vs Controllanti oltre | B38: =$K38*aida!B37 -> 0 | C38: =$K38*aida!C37 -> 0 | D38: =$K38*aida!D37 -> 0 | E38: =$K38*aida!E37 -> 0 | F38: =$K38*aida!F37 -> 0 | G38: =$K38*aida!G37 -> 0 | H38: =$K38*aida!H37 -> 0 | I38: =$K38*aida!I37 -> 0 | K38: 1 | L38: Immobilizzazioni extra-operative
A39: =aida!A38 -> B.III.2.d. Cred. vs imprese sottoposte al controllo delle controllanti entro | B39: =$K39*aida!B38 -> 0 | C39: =$K39*aida!C38 -> 0 | D39: =$K39*aida!D38 -> 0 | E39: =$K39*aida!E38 -> 0 | F39: =$K39*aida!F38 -> 0 | G39: =$K39*aida!G38 -> 0 | H39: =$K39*aida!H38 -> 0 | I39: =$K39*aida!I38 -> 0 | K39: 1 | L39: Crediti diversi
A40: =aida!A39 -> B.III.2.d. Cred. vs imprese sottoposte al controllo delle controllanti oltre | B40: =$K40*aida!B39 -> 0 | C40: =$K40*aida!C39 -> 0 | D40: =$K40*aida!D39 -> 0 | E40: =$K40*aida!E39 -> 0 | F40: =$K40*aida!F39 -> 0 | G40: =$K40*aida!G39 -> 0 | H40: =$K40*aida!H39 -> 0 | I40: =$K40*aida!I39 -> 0 | K40: 1 | L40: Crediti diversi
A41: =aida!A40 -> B.III.2.d.bis. Cred. vs Altri entro | B41: =$K41*aida!B40 -> 0 | C41: =$K41*aida!C40 -> 0 | D41: =$K41*aida!D40 -> 0 | E41: =$K41*aida!E40 -> 0 | F41: =$K41*aida!F40 -> 8192 | G41: =$K41*aida!G40 -> 8192 | H41: =$K41*aida!H40 -> 8192 | I41: =$K41*aida!I40 -> 0 | K41: 1 | L41: Crediti diversi
A42: =aida!A41 -> B.III.2.d.bis Cred. vs Altri oltre | B42: =$K42*aida!B41 -> 0 | C42: =$K42*aida!C41 -> 0 | D42: =$K42*aida!D41 -> 0 | E42: =$K42*aida!E41 -> 0 | F42: =$K42*aida!F41 -> 0 | G42: =$K42*aida!G41 -> 0 | H42: =$K42*aida!H41 -> 0 | I42: =$K42*aida!I41 -> 8192 | K42: 1 | L42: Crediti diversi
A43: =aida!A42 -> B.III. CREDITI FIN. A BREVE | B43: =$K43*aida!B42 -> 0 | C43: =$K43*aida!C42 -> 0 | D43: =$K43*aida!D42 -> 0 | E43: =$K43*aida!E42 -> 0 | F43: =$K43*aida!F42 -> 8192 | G43: =$K43*aida!G42 -> 8192 | H43: =$K43*aida!H42 -> 8192 | I43: =$K43*aida!I42 -> 0 | K43: 1
A44: =aida!A43 -> B.III. CREDITI FIN. A OLTRE | B44: =$K44*aida!B43 -> 0 | C44: =$K44*aida!C43 -> 0 | D44: =$K44*aida!D43 -> 0 | E44: =$K44*aida!E43 -> 0 | F44: =$K44*aida!F43 -> 0 | G44: =$K44*aida!G43 -> 0 | H44: =$K44*aida!H43 -> 0 | I44: =$K44*aida!I43 -> 8192 | K44: 1
A45: =aida!A44 -> B.III.3. Altri titoli | B45: =$K45*aida!B44 -> 0 | C45: =$K45*aida!C44 -> 0 | D45: =$K45*aida!D44 -> 0 | E45: =$K45*aida!E44 -> 0 | F45: =$K45*aida!F44 -> 0 | G45: =$K45*aida!G44 -> 0 | H45: =$K45*aida!H44 -> 0 | I45: =$K45*aida!I44 -> 0 | K45: 1 | L45: Partecipazioni
A46: =aida!A45 -> B.III.3.bis. Azioni proprie | B46: =$K46*aida!B45 -> 0 | C46: =$K46*aida!C45 -> 0 | D46: =$K46*aida!D45 -> 0 | E46: =$K46*aida!E45 -> 0 | F46: =$K46*aida!F45 -> 0 | G46: =$K46*aida!G45 -> 0 | H46: =$K46*aida!H45 -> 0 | I46: =$K46*aida!I45 -> 0 | K46: -1 | L46: Azioni proprie e partecipazioni in controllanti
A47: =aida!A46 -> B.III.4. Strumenti finanziari derivati attivi | B47: =$K47*aida!B46 -> 0 | C47: =$K47*aida!C46 -> 0 | D47: =$K47*aida!D46 -> 0 | E47: =$K47*aida!E46 -> 0 | F47: =$K47*aida!F46 -> 0 | G47: =$K47*aida!G46 -> 0 | H47: =$K47*aida!H46 -> 0 | I47: =$K47*aida!I46 -> 0 | K47: 1
A48: =aida!A47 -> Azioni proprie DI CUI: Val nominale | B48: =$K48*aida!B47 -> 0 | C48: =$K48*aida!C47 -> 0 | D48: =$K48*aida!D47 -> 0 | E48: =$K48*aida!E47 -> 0 | F48: =$K48*aida!F47 -> 0 | G48: =$K48*aida!G47 -> 0 | H48: =$K48*aida!H47 -> 0 | I48: =$K48*aida!I47 -> 0 | K48: 1
A50: =aida!A48 -> C. ATTIVO CIRCOLANTE | B50: =$K50*aida!B48 -> 9864960 | C50: =$K50*aida!C48 -> 11304972 | D50: =$K50*aida!D48 -> 11040279 | E50: =$K50*aida!E48 -> 8568239 | F50: =$K50*aida!F48 -> 7656738 | G50: =$K50*aida!G48 -> 6668572 | H50: =$K50*aida!H48 -> 5217184 | I50: =$K50*aida!I48 -> 5218727 | K50: 1
A51: =aida!A49 -> C.I. TOTALE RIMANENZE | B51: =$K51*aida!B49 -> 4608814 | C51: =$K51*aida!C49 -> 5103684 | D51: =$K51*aida!D49 -> 5250264 | E51: =$K51*aida!E49 -> 2924371 | F51: =$K51*aida!F49 -> 2556678 | G51: =$K51*aida!G49 -> 3010721 | H51: =$K51*aida!H49 -> 2422241 | I51: =$K51*aida!I49 -> 2070635 | K51: 1
A52: =aida!A50 -> C.I.1. Materie prime | B52: =$K52*aida!B50 -> 401813 | C52: =$K52*aida!C50 -> 259874 | D52: =$K52*aida!D50 -> 395324 | E52: =$K52*aida!E50 -> 233185 | F52: =$K52*aida!F50 -> 153593 | G52: =$K52*aida!G50 -> 229845 | H52: =$K52*aida!H50 -> 135786 | I52: =$K52*aida!I50 -> 170823 | K52: 1 | L52: Magazzino
A53: =aida!A51 -> C.I.2. Prodotti semilav./in corso | B53: =$K53*aida!B51 -> 3664689 | C53: =$K53*aida!C51 -> 4140030 | D53: =$K53*aida!D51 -> 4081340 | E53: =$K53*aida!E51 -> 2338118 | F53: =$K53*aida!F51 -> 1996776 | G53: =$K53*aida!G51 -> 2711561 | H53: =$K53*aida!H51 -> 2072725 | I53: =$K53*aida!I51 -> 1739894 | K53: 1 | L53: Magazzino
A54: =aida!A52 -> C.I.3. Lavori in corso | B54: =$K54*aida!B52 -> 0 | C54: =$K54*aida!C52 -> 0 | D54: =$K54*aida!D52 -> 0 | E54: =$K54*aida!E52 -> 0 | F54: =$K54*aida!F52 -> 0 | G54: =$K54*aida!G52 -> 0 | H54: =$K54*aida!H52 -> 0 | I54: =$K54*aida!I52 -> 0 | K54: 1 | L54: Magazzino
A55: =aida!A53 -> C.I.4. Prodotti finiti | B55: =$K55*aida!B53 -> 542312 | C55: =$K55*aida!C53 -> 640442 | D55: =$K55*aida!D53 -> 773600 | E55: =$K55*aida!E53 -> 353068 | F55: =$K55*aida!F53 -> 406309 | G55: =$K55*aida!G53 -> 69315 | H55: =$K55*aida!H53 -> 213730 | I55: =$K55*aida!I53 -> 159918 | K55: 1 | L55: Magazzino
A56: =aida!A54 -> C.I.5. Acconti | B56: =$K56*aida!B54 -> 0 | C56: =$K56*aida!C54 -> 63338 | D56: =$K56*aida!D54 -> 0 | E56: =$K56*aida!E54 -> 0 | F56: =$K56*aida!F54 -> 0 | G56: =$K56*aida!G54 -> 0 | H56: =$K56*aida!H54 -> 0 | I56: =$K56*aida!I54 -> 0 | K56: 1 | L56: Altre attività operative correnti
A57: =aida!A55 -> Immobilizzazioni materiali destinate alla vendita | B57: =$K57*aida!B55 -> 0 | C57: =$K57*aida!C55 -> 0 | D57: =$K57*aida!D55 -> 0 | E57: =$K57*aida!E55 -> 0 | F57: =$K57*aida!F55 -> 0 | G57: =$K57*aida!G55 -> 0 | H57: =$K57*aida!H55 -> 0 | I57: =$K57*aida!I55 -> 0 | K57: 1 | L57: Immobilizzazioni materiali nette
A58: =aida!A56 -> C.II. TOTALE CREDITI | B58: =$K58*aida!B56 -> 5013716 | C58: =$K58*aida!C56 -> 5309746 | D58: =$K58*aida!D56 -> 4632483 | E58: =$K58*aida!E56 -> 3374197 | F58: =$K58*aida!F56 -> 3111429 | G58: =$K58*aida!G56 -> 3053922 | H58: =$K58*aida!H56 -> 2457865 | I58: =$K58*aida!I56 -> 2435304 | K58: 1
A59: =aida!A57 -> C.II.1. Cred. vs Clienti entro | B59: =$K59*aida!B57 -> 4256399 | C59: =$K59*aida!C57 -> 3896776 | D59: =$K59*aida!D57 -> 2966203 | E59: =$K59*aida!E57 -> 3180616 | F59: =$K59*aida!F57 -> 2787212 | G59: =$K59*aida!G57 -> 2642901 | H59: =$K59*aida!H57 -> 2353521 | I59: =$K59*aida!I57 -> 2381302 | K59: 1 | L59: Crediti verso clienti
A60: =aida!A58 -> C.II.1. Cred. vs Clienti oltre | B60: =$K60*aida!B58 -> 0 | C60: =$K60*aida!C58 -> 0 | D60: =$K60*aida!D58 -> 0 | E60: =$K60*aida!E58 -> 0 | F60: =$K60*aida!F58 -> 0 | G60: =$K60*aida!G58 -> 0 | H60: =$K60*aida!H58 -> 0 | I60: =$K60*aida!I58 -> 0 | K60: 1 | L60: Crediti verso clienti
A61: =aida!A59 -> C.II.2. Cred. vs Controllate entro | B61: =$K61*aida!B59 -> 0 | C61: =$K61*aida!C59 -> 0 | D61: =$K61*aida!D59 -> 0 | E61: =$K61*aida!E59 -> 0 | F61: =$K61*aida!F59 -> 0 | G61: =$K61*aida!G59 -> 0 | H61: =$K61*aida!H59 -> 0 | I61: =$K61*aida!I59 -> 0 | K61: 1 | L61: Crediti vs controllate e collegate
A62: =aida!A60 -> C.II.2. Cred. vs Controllate oltre | B62: =$K62*aida!B60 -> 0 | C62: =$K62*aida!C60 -> 0 | D62: =$K62*aida!D60 -> 0 | E62: =$K62*aida!E60 -> 0 | F62: =$K62*aida!F60 -> 0 | G62: =$K62*aida!G60 -> 0 | H62: =$K62*aida!H60 -> 0 | I62: =$K62*aida!I60 -> 0 | K62: 1 | L62: Crediti vs controllate e collegate
A63: =aida!A61 -> C.II.3. Cred. vs Collegate entro | B63: =$K63*aida!B61 -> 0 | C63: =$K63*aida!C61 -> 0 | D63: =$K63*aida!D61 -> 0 | E63: =$K63*aida!E61 -> 0 | F63: =$K63*aida!F61 -> 0 | G63: =$K63*aida!G61 -> 0 | H63: =$K63*aida!H61 -> 0 | I63: =$K63*aida!I61 -> 0 | K63: 1 | L63: Crediti vs controllate e collegate
A64: =aida!A62 -> C.II.3. Cred. vs Collegate oltre | B64: =$K64*aida!B62 -> 0 | C64: =$K64*aida!C62 -> 0 | D64: =$K64*aida!D62 -> 0 | E64: =$K64*aida!E62 -> 0 | F64: =$K64*aida!F62 -> 0 | G64: =$K64*aida!G62 -> 0 | H64: =$K64*aida!H62 -> 0 | I64: =$K64*aida!I62 -> 0 | K64: 1 | L64: Crediti vs controllate e collegate
A65: =aida!A63 -> C.II.4. Cred. vs Controllanti entro | B65: =$K65*aida!B63 -> 0 | C65: =$K65*aida!C63 -> 0 | D65: =$K65*aida!D63 -> 0 | E65: =$K65*aida!E63 -> 0 | F65: =$K65*aida!F63 -> 0 | G65: =$K65*aida!G63 -> 0 | H65: =$K65*aida!H63 -> 0 | I65: =$K65*aida!I63 -> 0 | K65: 1 | L65: Crediti vs controllate e collegate
A66: =aida!A64 -> C.II.4. Cred. vs Controllanti oltre | B66: =$K66*aida!B64 -> 0 | C66: =$K66*aida!C64 -> 0 | D66: =$K66*aida!D64 -> 0 | E66: =$K66*aida!E64 -> 0 | F66: =$K66*aida!F64 -> 0 | G66: =$K66*aida!G64 -> 0 | H66: =$K66*aida!H64 -> 0 | I66: =$K66*aida!I64 -> 0 | K66: 1 | L66: Crediti vs controllate e collegate
A67: =aida!A65 -> C.II.5. Cred. vs imprese sottoposte al controllo delle controllanti entro | B67: =$K67*aida!B65 -> 0 | C67: =$K67*aida!C65 -> 0 | D67: =$K67*aida!D65 -> 0 | E67: =$K67*aida!E65 -> 0 | F67: =$K67*aida!F65 -> 0 | G67: =$K67*aida!G65 -> 0 | H67: =$K67*aida!H65 -> 0 | I67: =$K67*aida!I65 -> 0 | K67: 1 | L67: Crediti vs controllate e collegate
A68: =aida!A66 -> C.II.5. Cred. vs imprese sottoposte al controllo delle controllanti oltre | B68: =$K68*aida!B66 -> 0 | C68: =$K68*aida!C66 -> 0 | D68: =$K68*aida!D66 -> 0 | E68: =$K68*aida!E66 -> 0 | F68: =$K68*aida!F66 -> 0 | G68: =$K68*aida!G66 -> 0 | H68: =$K68*aida!H66 -> 0 | I68: =$K68*aida!I66 -> 0 | K68: 1 | L68: Crediti vs controllate e collegate
A69: =aida!A67 -> C.II.5.bis. Cred. tributari entro | B69: =$K69*aida!B67 -> 11273 | C69: =$K69*aida!C67 -> 121727 | D69: =$K69*aida!D67 -> 578618 | E69: =$K69*aida!E67 -> 112666 | F69: =$K69*aida!F67 -> 284700 | G69: =$K69*aida!G67 -> 175791 | H69: =$K69*aida!H67 -> 57954 | I69: =$K69*aida!I67 -> 4758 | K69: 1 | L69: Crediti fisco-previdenziali
A70: =aida!A68 -> C.II.5.bis. Cred. tributari oltre | B70: =$K70*aida!B68 -> 12001 | C70: =$K70*aida!C68 -> 21254 | D70: =$K70*aida!D68 -> 127045 | E70: =$K70*aida!E68 -> 34606 | F70: =$K70*aida!F68 -> 0 | G70: =$K70*aida!G68 -> 0 | H70: =$K70*aida!H68 -> 0 | I70: =$K70*aida!I68 -> 0 | K70: 1 | L70: Crediti fisco-previdenziali
... A74: =aida!A72 -> C.II.5.quater. Cred. verso altri oltre | B74: =$K74*aida!B72 -> 613458 | C74: =$K74*aida!C72 -> 1159030 | D74: =$K74*aida!D72 -> 909287 | E74: =$K74*aida!E72 -> 8292 | F74: =$K74*aida!F72 -> 0 | G74: =$K74*aida!G72 -> 0 | H74: =$K74*aida!H72 -> 0 | I74: =$K74*aida!I72 -> 0 | K74: 1 | L74: Altre attività operative correnti
A75: =aida!A73 -> C.II. Crediti a breve | B75: =$K75*aida!B73 -> 4388257 | C75: =$K75*aida!C73 -> 4129462 | D75: =$K75*aida!D73 -> 3596151 | E75: =$K75*aida!E73 -> 3331299 | F75: =$K75*aida!F73 -> 3111429 | G75: =$K75*aida!G73 -> 3053922 | H75: =$K75*aida!H73 -> 2457865 | I75: =$K75*aida!I73 -> 2435304 | K75: 1
A76: =aida!A74 -> Crediti per imposte anticipate | B76: =$K76*aida!B74 -> 0 | C76: =$K76*aida!C74 -> 0 | D76: =$K76*aida!D74 -> 0 | E76: =$K76*aida!E74 -> 0 | F76: =$K76*aida!F74 -> 0 | G76: =$K76*aida!G74 -> 0 | H76: =$K76*aida!H74 -> 0 | I76: =$K76*aida!I74 -> 0 | K76: 1
A77: =aida!A75 -> C.II. Crediti a oltre | B77: =$K77*aida!B75 -> 625459 | C77: =$K77*aida!C75 -> 1180284 | D77: =$K77*aida!D75 -> 1036332 | E77: =$K77*aida!E75 -> 42898 | F77: =$K77*aida!F75 -> 0 | G77: =$K77*aida!G75 -> 0 | H77: =$K77*aida!H75 -> 0 | I77: =$K77*aida!I75 -> 0 | K77: 1
A78: =aida!A76 -> C.III. TOTALE ATTIVITA' FINANZIARIE | B78: =$K78*aida!B76 -> 0 | C78: =$K78*aida!C76 -> 0 | D78: =$K78*aida!D76 -> 0 | E78: =$K78*aida!E76 -> 0 | F78: =$K78*aida!F76 -> 0 | G78: =$K78*aida!G76 -> 0 | H78: =$K78*aida!H76 -> 0 | I78: =$K78*aida!I76 -> 0 | K78: 1
A79: =aida!A77 -> C.III.1. Partec.ni in Controllate | B79: =$K79*aida!B77 -> 0 | C79: =$K79*aida!C77 -> 0 | D79: =$K79*aida!D77 -> 0 | E79: =$K79*aida!E77 -> 0 | F79: =$K79*aida!F77 -> 0 | G79: =$K79*aida!G77 -> 0 | H79: =$K79*aida!H77 -> 0 | I79: =$K79*aida!I77 -> 0 | K79: 1 | L79: Partecipazioni
A80: =aida!A78 -> C.III.2. Partec.ni in Collegate | B80: =$K80*aida!B78 -> 0 | C80: =$K80*aida!C78 -> 0 | D80: =$K80*aida!D78 -> 0 | E80: =$K80*aida!E78 -> 0 | F80: =$K80*aida!F78 -> 0 | G80: =$K80*aida!G78 -> 0 | H80: =$K80*aida!H78 -> 0 | I80: =$K80*aida!I78 -> 0 | K80: 1 | L80: Partecipazioni
A81: =aida!A79 -> C.III.3. Partec.ni in Controllanti | B81: =$K81*aida!B79 -> 0 | C81: =$K81*aida!C79 -> 0 | D81: =$K81*aida!D79 -> 0 | E81: =$K81*aida!E79 -> 0 | F81: =$K81*aida!F79 -> 0 | G81: =$K81*aida!G79 -> 0 | H81: =$K81*aida!H79 -> 0 | I81: =$K81*aida!I79 -> 0 | K81: 1 | L81: Partecipazioni
A82: =aida!A80 -> C.III.3.bis. Partec.ni in imprese sottoposte al controllo delle controllanti | B82: =$K82*aida!B80 -> 0 | C82: =$K82*aida!C80 -> 0 | D82: =$K82*aida!D80 -> 0 | E82: =$K82*aida!E80 -> 0 | F82: =$K82*aida!F80 -> 0 | G82: =$K82*aida!G80 -> 0 | H82: =$K82*aida!H80 -> 0 | I82: =$K82*aida!I80 -> 0 | K82: 1 | L82: Partecipazioni
A83: =aida!A81 -> C.III.4. Altre Partec.ni | B83: =$K83*aida!B81 -> 0 | C83: =$K83*aida!C81 -> 0 | D83: =$K83*aida!D81 -> 0 | E83: =$K83*aida!E81 -> 0 | F83: =$K83*aida!F81 -> 0 | G83: =$K83*aida!G81 -> 0 | H83: =$K83*aida!H81 -> 0 | I83: =$K83*aida!I81 -> 0 | K83: 1 | L83: Partecipazioni
A84: =aida!A82 -> C.III.4.bis. Azioni proprie | B84: =$K84*aida!B82 -> 0 | C84: =$K84*aida!C82 -> 0 | D84: =$K84*aida!D82 -> 0 | E84: =$K84*aida!E82 -> 0 | F84: =$K84*aida!F82 -> 0 | G84: =$K84*aida!G82 -> 0 | H84: =$K84*aida!H82 -> 0 | I84: =$K84*aida!I82 -> 0 | K84: 1 | L84: Partecipazioni
A85: =aida!A83 -> Azioni proprie DI CUI: Val nominale | B85: =$K85*aida!B83 -> 0 | C85: =$K85*aida!C83 -> 0 | D85: =$K85*aida!D83 -> 0 | E85: =$K85*aida!E83 -> 0 | F85: =$K85*aida!F83 -> 0 | G85: =$K85*aida!G83 -> 0 | H85: =$K85*aida!H83 -> 0 | I85: =$K85*aida!I83 -> 0 | K85: 1
A86: =aida!A84 -> C.III.5. Strumenti finanziari derivati attivi | B86: =$K86*aida!B84 -> 0 | C86: =$K86*aida!C84 -> 0 | D86: =$K86*aida!D84 -> 0 | E86: =$K86*aida!E84 -> 0 | F86: =$K86*aida!F84 -> 0 | G86: =$K86*aida!G84 -> 0 | H86: =$K86*aida!H84 -> 0 | I86: =$K86*aida!I84 -> 0 | K86: 1 | L86: Strumenti derivati attivi
A87: =aida!A85 -> C.III.6. Altri titoli | B87: =$K87*aida!B85 -> 0 | C87: =$K87*aida!C85 -> 0 | D87: =$K87*aida!D85 -> 0 | E87: =$K87*aida!E85 -> 0 | F87: =$K87*aida!F85 -> 0 | G87: =$K87*aida!G85 -> 0 | H87: =$K87*aida!H85 -> 0 | I87: =$K87*aida!I85 -> 0 | K87: 1 | L87: Immobilizzazioni extra-operative
A88: =aida!A86 -> C.III.7. Attività finanziarie per la gestione accentrata della tesoreria | B88: =$K88*aida!B86 -> 0 | C88: =$K88*aida!C86 -> 0 | D88: =$K88*aida!D86 -> 0 | E88: =$K88*aida!E86 -> 0 | F88: =$K88*aida!F86 -> 0 | G88: =$K88*aida!G86 -> 0 | H88: =$K88*aida!H86 -> 0 | I88: =$K88*aida!I86 -> 0 | K88: 1 | L88: Attività di tesoreria
A89: =aida!A87 -> C.IV. TOT. DISPON. LIQUIDE | B89: =$K89*aida!B87 -> 242430 | C89: =$K89*aida!C87 -> 891542 | D89: =$K89*aida!D87 -> 1157532 | E89: =$K89*aida!E87 -> 2269671 | F89: =$K89*aida!F87 -> 1988631 | G89: =$K89*aida!G87 -> 603929 | H89: =$K89*aida!H87 -> 337078 | I89: =$K89*aida!I87 -> 712788 | K89: 1
A90: =aida!A88 -> C.IV.1. Depositi bancari | B90: =$K90*aida!B88 -> 241919 | C90: =$K90*aida!C88 -> 891422 | D90: =$K90*aida!D88 -> 1157445 | E90: =$K90*aida!E88 -> 2269599 | F90: =$K90*aida!F88 -> 1988227 | G90: =$K90*aida!G88 -> 603874 | H90: =$K90*aida!H88 -> 336843 | I90: =$K90*aida!I88 -> 712192 | K90: 1 | L90: Attività di tesoreria
A91: =aida!A89 -> C.IV.2. Assegni | B91: =$K91*aida!B89 -> 0 | C91: =$K91*aida!C89 -> 0 | D91: =$K91*aida!D89 -> 0 | E91: =$K91*aida!E89 -> 0 | F91: =$K91*aida!F89 -> 0 | G91: =$K91*aida!G89 -> 0 | H91: =$K91*aida!H89 -> 0 | I91: =$K91*aida!I89 -> 0 | K91: 1 | L91: Attività di tesoreria
A92: =aida!A90 -> C.IV.3. Denaro in cassa | B92: =$K92*aida!B90 -> 511 | C92: =$K92*aida!C90 -> 120 | D92: =$K92*aida!D90 -> 87 | E92: =$K92*aida!E90 -> 72 | F92: =$K92*aida!F90 -> 404 | G92: =$K92*aida!G90 -> 55 | H92: =$K92*aida!H90 -> 235 | I92: =$K92*aida!I90 -> 596 | K92: 1 | L92: Attività di tesoreria
A93: =aida!A91 -> D. RATEI E RISCONTI | B93: =$K93*aida!B91 -> 82949 | C93: =$K93*aida!C91 -> 66553 | D93: =$K93*aida!D91 -> 67834 | E93: =$K93*aida!E91 -> 70670 | F93: =$K93*aida!F91 -> 65092 | G93: =$K93*aida!G91 -> 26537 | H93: =$K93*aida!H91 -> 36724 | I93: =$K93*aida!I91 -> 24511 | K93: 1 | L93: Altre attività operative correnti
A94: =aida!A92 -> Disaggio su prestiti | B94: =$K94*aida!B92 -> 0 | C94: =$K94*aida!C92 -> 0 | D94: =$K94*aida!D92 -> 0 | E94: =$K94*aida!E92 -> 0 | F94: =$K94*aida!F92 -> 0 | G94: =$K94*aida!G92 -> 0 | H94: =$K94*aida!H92 -> 0 | I94: =$K94*aida!I92 -> 0 | K94: 1
A95: =aida!A93 -> TOTALE ATTIVO | B95: =$K95*aida!B93 -> 18790859 | C95: =$K95*aida!C93 -> 20554377 | D95: =$K95*aida!D93 -> 20723060 | E95: =$K95*aida!E93 -> 18204611 | F95: =$K95*aida!F93 -> 14795011 | G95: =$K95*aida!G93 -> 9311398 | H95: =$K95*aida!H93 -> 6455031 | I95: =$K95*aida!I93 -> 6151737 | K95: 1
A97: =aida!A94 -> Passivo
A98: =aida!A95 -> PATRIMONIO NETTO | B98: =$K98*aida!B95 -> 0 | C98: =$K98*aida!C95 -> 0 | D98: =$K98*aida!D95 -> 0 | E98: =$K98*aida!E95 -> 0 | F98: =$K98*aida!F95 -> 0 | G98: =$K98*aida!G95 -> 0 | H98: =$K98*aida!H95 -> 0 | I98: =$K98*aida!I95 -> 0 | K98: 1
A99: =aida!A96 -> A. TOTALE PATRIMONIO NETTO | B99: =$K99*aida!B96 -> 5757287 | C99: =$K99*aida!C96 -> 5227552 | D99: =$K99*aida!D96 -> 4660887 | E99: =$K99*aida!E96 -> 4082303 | F99: =$K99*aida!F96 -> 3206001 | G99: =$K99*aida!G96 -> 2384718 | H99: =$K99*aida!H96 -> 1733081 | I99: =$K99*aida!I96 -> 1062658 | K99: 1
A100: =aida!A97 -> A.I. Capitale sociale | B100: =$K100*aida!B97 -> 140000 | C100: =$K100*aida!C97 -> 140000 | D100: =$K100*aida!D97 -> 140000 | E100: =$K100*aida!E97 -> 140000 | F100: =$K100*aida!F97 -> 140000 | G100: =$K100*aida!G97 -> 140000 | H100: =$K100*aida!H97 -> 140000 | I100: =$K100*aida!I97 -> 140000 | K100: 1 | L100: Capitale conferito dai soci
A101: =aida!A98 -> di cui: Versamenti soci in c/capitale | B101: =$K101*aida!B98 -> 0 | C101: =$K101*aida!C98 -> 0 | D101: =$K101*aida!D98 -> 0 | E101: =$K101*aida!E98 -> 0 | F101: =$K101*aida!F98 -> 0 | G101: =$K101*aida!G98 -> 0 | H101: =$K101*aida!H98 -> 0 | I101: =$K101*aida!I98 -> 0 | K101: 1
A102: =aida!A99 -> di cui: Versamenti in c/futuro aumento di capitale | B102: =$K102*aida!B99 -> 0 | C102: =$K102*aida!C99 -> 0 | D102: =$K102*aida!D99 -> 0 | E102: =$K102*aida!E99 -> 0 | F102: =$K102*aida!F99 -> 0 | G102: =$K102*aida!G99 -> 0 | H102: =$K102*aida!H99 -> 0 | I102: =$K102*aida!I99 -> 0 | K102: 1
A103: =aida!A100 -> di cui: Versamenti in c/capitale | B103: =$K103*aida!B100 -> 0 | C103: =$K103*aida!C100 -> 0 | D103: =$K103*aida!D100 -> 0 | E103: =$K103*aida!E100 -> 0 | F103: =$K103*aida!F100 -> 0 | G103: =$K103*aida!G100 -> 0 | H103: =$K103*aida!H100 -> 0 | I103: =$K103*aida!I100 -> 0 | K103: 1
A104: =aida!A101 -> di cui: Versamenti a copertura perdite | B104: =$K104*aida!B101 -> 0 | C104: =$K104*aida!C101 -> 0 | D104: =$K104*aida!D101 -> 0 | E104: =$K104*aida!E101 -> 0 | F104: =$K104*aida!F101 -> 0 | G104: =$K104*aida!G101 -> 0 | H104: =$K104*aida!H101 -> 0 | I104: =$K104*aida!I101 -> 0 | K104: 1
A105: =aida!A102 -> A.II. Riserva da sovrapprezzo | B105: =$K105*aida!B102 -> 0 | C105: =$K105*aida!C102 -> 0 | D105: =$K105*aida!D102 -> 0 | E105: =$K105*aida!E102 -> 0 | F105: =$K105*aida!F102 -> 0 | G105: =$K105*aida!G102 -> 0 | H105: =$K105*aida!H102 -> 0 | I105: =$K105*aida!I102 -> 0 | K105: 1 | L105: Capitale conferito dai soci
A106: =aida!A103 -> A.III. Riserva di rivalutazione | B106: =$K106*aida!B103 -> 0 | C106: =$K106*aida!C103 -> 0 | D106: =$K106*aida!D103 -> 0 | E106: =$K106*aida!E103 -> 0 | F106: =$K106*aida!F103 -> 0 | G106: =$K106*aida!G103 -> 0 | H106: =$K106*aida!H103 -> 0 | I106: =$K106*aida!I103 -> 0 | K106: 1 | L106: Riserve da rivalutazione
...

Sheet RC
B2: Stato Patrimoniale Attivo | C2: =case!B1 -> 31/12/2024 | D2: =case!C1 -> 31/12/2023 | E2: =case!D1 -> 31/12/2022 | F2: =case!E1 -> 31/12/2021 | G2: =case!F1 -> 31/12/2020 | H2: =case!G1 -> 31/12/2019 | I2: =case!H1 -> 31/12/2018 | J2: =case!I1 -> 31/12/2017
B3: Attività operative
B4: Attività operative correnti
B5: Crediti verso clienti | C5: =SUMIF(case!$L:$L,$B5,case!B:B) -> 4256399 | D5: =SUMIF(case!$L:$L,$B5,case!C:C) -> 3896776 | E5: =SUMIF(case!$L:$L,$B5,case!D:D) -> 2966203 | F5: =SUMIF(case!$L:$L,$B5,case!E:E) -> 3180616 | G5: =SUMIF(case!$L:$L,$B5,case!F:F) -> 2787212 | H5: =SUMIF(case!$L:$L,$B5,case!G:G) -> 2642901 | I5: =SUMIF(case!$L:$L,$B5,case!H:H) -> 2353521 | J5: =SUMIF(case!$L:$L,$B5,case!I:I) -> 2381302
B6: Magazzino | C6: =SUMIF(case!$L:$L,$B6,case!B:B) -> 4608814 | D6: =SUMIF(case!$L:$L,$B6,case!C:C) -> 5040346 | E6: =SUMIF(case!$L:$L,$B6,case!D:D) -> 5250264 | F6: =SUMIF(case!$L:$L,$B6,case!E:E) -> 2924371 | G6: =SUMIF(case!$L:$L,$B6,case!F:F) -> 2556678 | H6: =SUMIF(case!$L:$L,$B6,case!G:G) -> 3010721 | I6: =SUMIF(case!$L:$L,$B6,case!H:H) -> 2422241 | J6: =SUMIF(case!$L:$L,$B6,case!I:I) -> 2070635
B7: Altre attività operative correnti | C7: =SUMIF(case!$L:$L,$B7,case!B:B) -> 816992 | D7: =SUMIF(case!$L:$L,$B7,case!C:C) -> 1399880 | E7: =SUMIF(case!$L:$L,$B7,case!D:D) -> 1028451 | F7: =SUMIF(case!$L:$L,$B7,case!E:E) -> 116979 | G7: =SUMIF(case!$L:$L,$B7,case!F:F) -> 104609 | H7: =SUMIF(case!$L:$L,$B7,case!G:G) -> 261767 | I7: =SUMIF(case!$L:$L,$B7,case!H:H) -> 83114 | J7: =SUMIF(case!$L:$L,$B7,case!I:I) -> 73755
B8: Totale attività operative correnti | C8: =SUM(C5:C7) -> 9682205 | D8: =SUM(D5:D7) -> 10337002 | E8: =SUM(E5:E7) -> 9244918 | F8: =SUM(F5:F7) -> 6221966 | G8: =SUM(G5:G7) -> 5448499 | H8: =SUM(H5:H7) -> 5915389 | I8: =SUM(I5:I7) -> 4858876 | J8: =SUM(J5:J7) -> 4525692
B9: Immobilizzazioni operative nette
B10: Immobilizzazioni materiali nette | C10: =SUMIF(case!$L:$L,$B10,case!B:B) -> 8694725 | D10: =SUMIF(case!$L:$L,$B10,case!C:C) -> 9017770 | E10: =SUMIF(case!$L:$L,$B10,case!D:D) -> 9416528 | F10: =SUMIF(case!$L:$L,$B10,case!E:E) -> 9430510 | G10: =SUMIF(case!$L:$L,$B10,case!F:F) -> 7025024 | H10: =SUMIF(case!$L:$L,$B10,case!G:G) -> 2594042 | I10: =SUMIF(case!$L:$L,$B10,case!H:H) -> 1186419 | J10: =SUMIF(case!$L:$L,$B10,case!I:I) -> 891818
B11: Immobilizzazioni immateriali nette | C11: =SUMIF(case!$L:$L,$B11,case!B:B) -> 89523 | D11: =SUMIF(case!$L:$L,$B11,case!C:C) -> 106380 | E11: =SUMIF(case!$L:$L,$B11,case!D:D) -> 139717 | F11: =SUMIF(case!$L:$L,$B11,case!E:E) -> 76490 | G11: =SUMIF(case!$L:$L,$B11,case!F:F) -> 33453 | H11: =SUMIF(case!$L:$L,$B11,case!G:G) -> 7543 | I11: =SUMIF(case!$L:$L,$B11,case!H:H) -> 0 | J11: =SUMIF(case!$L:$L,$B11,case!I:I) -> 1977
B12: Totale immobilizzazioni operative nette | C12: =SUM(C10:C11) -> 8784248 | D12: =SUM(D10:D11) -> 9124150 | E12: =SUM(E10:E11) -> 9556245 | F12: =SUM(F10:F11) -> 9507000 | G12: =SUM(G10:G11) -> 7058477 | H12: =SUM(H10:H11) -> 2601585 | I12: =SUM(I10:I11) -> 1186419 | J12: =SUM(J10:J11) -> 893795
B13: Altre attività operative immobilizzate
B14: Crediti diversi | C14: =SUMIF(case!$L:$L,$B14,case!B:B) -> 0 | D14: =SUMIF(case!$L:$L,$B14,case!C:C) -> 0 | E14: =SUMIF(case!$L:$L,$B14,case!D:D) -> 0 | F14: =SUMIF(case!$L:$L,$B14,case!E:E) -> 0 | G14: =SUMIF(case!$L:$L,$B14,case!F:F) -> 8192 | H14: =SUMIF(case!$L:$L,$B14,case!G:G) -> 8192 | I14: =SUMIF(case!$L:$L,$B14,case!H:H) -> 8192 | J14: =SUMIF(case!$L:$L,$B14,case!I:I) -> 8192
B15: Totale altre attività operative immobilizzate | C15: =SUM(C14) -> 0 | D15: =SUM(D14) -> 0 | E15: =SUM(E14) -> 0 | F15: =SUM(F14) -> 0 | G15: =SUM(G14) -> 8192 | H15: =SUM(H14) -> 8192 | I15: =SUM(I14) -> 8192 | J15: =SUM(J14) -> 8192
B16: Totale attività operative | C16: =C8+C12+C15 -> 18466453 | D16: =D8+D12+D15 -> 19461152 | E16: =E8+E12+E15 -> 18801163 | F16: =F8+F12+F15 -> 15728966 | G16: =G8+G12+G15 -> 12515168 | H16: =H8+H12+H15 -> 8525166 | I16: =I8+I12+I15 -> 6053487 | J16: =J8+J12+J15 -> 5427679
B18: Attività fiscali
B19: Crediti fisco-previdenziali | C19: =SUMIF(case!$L:$L,$B19,case!B:B) -> 23274 | D19: =SUMIF(case!$L:$L,$B19,case!C:C) -> 142981 | E19: =SUMIF(case!$L:$L,$B19,case!D:D) -> 705663 | F19: =SUMIF(case!$L:$L,$B19,case!E:E) -> 147272 | G19: =SUMIF(case!$L:$L,$B19,case!F:F) -> 284700 | H19: =SUMIF(case!$L:$L,$B19,case!G:G) -> 175791 | I19: =SUMIF(case!$L:$L,$B19,case!H:H) -> 57954 | J19: =SUMIF(case!$L:$L,$B19,case!I:I) -> 4758
B20: Attività per imposte anticipate | C20: =SUMIF(case!$L:$L,$B20,case!B:B) -> 0 | D20: =SUMIF(case!$L:$L,$B20,case!C:C) -> 0 | E20: =SUMIF(case!$L:$L,$B20,case!D:D) -> 0 | F20: =SUMIF(case!$L:$L,$B20,case!E:E) -> 0 | G20: =SUMIF(case!$L:$L,$B20,case!F:F) -> 0 | H20: =SUMIF(case!$L:$L,$B20,case!G:G) -> 0 | I20: =SUMIF(case!$L:$L,$B20,case!H:H) -> 0 | J20: =SUMIF(case!$L:$L,$B20,case!I:I) -> 0
B21: Totale attività fiscali | C21: =SUM(C19:C20) -> 23274 | D21: =SUM(D19:D20) -> 142981 | E21: =SUM(E19:E20) -> 705663 | F21: =SUM(F19:F20) -> 147272 | G21: =SUM(G19:G20) -> 284700 | H21: =SUM(H19:H20) -> 175791 | I21: =SUM(I19:I20) -> 57954 | J21: =SUM(J19:J20) -> 4758
B23: Attività accessorie
B24: Immobilizzazioni extra-operative | C24: =SUMIF(case!$L:$L,$B24,case!B:B) -> 0 | D24: =SUMIF(case!$L:$L,$B24,case!C:C) -> 0 | E24: =SUMIF(case!$L:$L,$B24,case!D:D) -> 0 | F24: =SUMIF(case!$L:$L,$B24,case!E:E) -> 0 | G24: =SUMIF(case!$L:$L,$B24,case!F:F) -> 0 | H24: =SUMIF(case!$L:$L,$B24,case!G:G) -> 0 | I24: =SUMIF(case!$L:$L,$B24,case!H:H) -> 0 | J24: =SUMIF(case!$L:$L,$B24,case!I:I) -> 0
B25: Partecipazioni | C25: =SUMIF(case!$L:$L,$B25,case!B:B) -> 58702 | D25: =SUMIF(case!$L:$L,$B25,case!C:C) -> 58702 | E25: =SUMIF(case!$L:$L,$B25,case!D:D) -> 58702 | F25: =SUMIF(case!$L:$L,$B25,case!E:E) -> 58702 | G25: =SUMIF(case!$L:$L,$B25,case!F:F) -> 6512 | H25: =SUMIF(case!$L:$L,$B25,case!G:G) -> 6512 | I25: =SUMIF(case!$L:$L,$B25,case!H:H) -> 6512 | J25: =SUMIF(case!$L:$L,$B25,case!I:I) -> 6512
B26: Crediti vs controllate e collegate | C26: =SUMIF(case!$L:$L,$B26,case!B:B) -> 0 | D26: =SUMIF(case!$L:$L,$B26,case!C:C) -> 0 | E26: =SUMIF(case!$L:$L,$B26,case!D:D) -> 0 | F26: =SUMIF(case!$L:$L,$B26,case!E:E) -> 0 | G26: =SUMIF(case!$L:$L,$B26,case!F:F) -> 0 | H26: =SUMIF(case!$L:$L,$B26,case!G:G) -> 0 | I26: =SUMIF(case!$L:$L,$B26,case!H:H) -> 0 | J26: =SUMIF(case!$L:$L,$B26,case!I:I) -> 0
B27: Totale attività accessorie | C27: =SUM(C24:C26) -> 58702 | D27: =SUM(D24:D26) -> 58702 | E27: =SUM(E24:E26) -> 58702 | F27: =SUM(F24:F26) -> 58702 | G27: =SUM(G24:G26) -> 6512 | H27: =SUM(H24:H26) -> 6512 | I27: =SUM(I24:I26) -> 6512 | J27: =SUM(J24:J26) -> 6512
B29: Attività finanziarie
B30: Riserve strategiche di liquidità | C30: =SUMIF(case!$L:$L,$B30,case!B:B) -> 0 | D30: =SUMIF(case!$L:$L,$B30,case!C:C) -> 0 | E30: =SUMIF(case!$L:$L,$B30,case!D:D) -> 0 | F30: =SUMIF(case!$L:$L,$B30,case!E:E) -> 0 | G30: =SUMIF(case!$L:$L,$B30,case!F:F) -> 0 | H30: =SUMIF(case!$L:$L,$B30,case!G:G) -> 0 | I30: =SUMIF(case!$L:$L,$B30,case!H:H) -> 0 | J30: =SUMIF(case!$L:$L,$B30,case!I:I) -> 0
B31: Attività di tesoreria | C31: =SUMIF(case!$L:$L,$B31,case!B:B) -> 242430 | D31: =SUMIF(case!$L:$L,$B31,case!C:C) -> 891542 | E31: =SUMIF(case!$L:$L,$B31,case!D:D) -> 1157532 | F31: =SUMIF(case!$L:$L,$B31,case!E:E) -> 2269671 | G31: =SUMIF(case!$L:$L,$B31,case!F:F) -> 1988631 | H31: =SUMIF(case!$L:$L,$B31,case!G:G) -> 603929 | I31: =SUMIF(case!$L:$L,$B31,case!H:H) -> 337078 | J31: =SUMIF(case!$L:$L,$B31,case!I:I) -> 712788
B32: Strumenti derivati attivi | C32: =SUMIF(case!$L:$L,$B32,case!B:B) -> 0 | D32: =SUMIF(case!$L:$L,$B32,case!C:C) -> 0 | E32: =SUMIF(case!$L:$L,$B32,case!D:D) -> 0 | F32: =SUMIF(case!$L:$L,$B32,case!E:E) -> 0 | G32: =SUMIF(case!$L:$L,$B32,case!F:F) -> 0 | H32: =SUMIF(case!$L:$L,$B32,case!G:G) -> 0 | I32: =SUMIF(case!$L:$L,$B32,case!H:H) -> 0 | J32: =SUMIF(case!$L:$L,$B32,case!I:I) -> 0
B33: Totale attività finanziarie | C33: =SUM(C30:C32) -> 242430 | D33: =SUM(D30:D32) -> 891542 | E33: =SUM(E30:E32) -> 1157532 | F33: =SUM(F30:F32) -> 2269671 | G33: =SUM(G30:G32) -> 1988631 | H33: =SUM(H30:H32) -> 603929 | I33: =SUM(I30:I32) -> 337078 | J33: =SUM(J30:J32) -> 712788
B35: Totale attivo | C35: =C16+C21+C27+C33 -> 18790859 | D35: =D16+D21+D27+D33 -> 20554377 | E35: =E16+E21+E27+E33 -> 20723060 | F35: =F16+F21+F27+F33 -> 18204611 | G35: =G16+G21+G27+G33 -> 14795011 | H35: =H16+H21+H27+H33 -> 9311398 | I35: =I16+I21+I27+I33 -> 6455031 | J35: =J16+J21+J27+J33 -> 6151737
B37: Check con totale attivo AIDA | C37: =case!B95 -> 18790859 | D37: =case!C95 -> 20554377 | E37: =case!D95 -> 20723060 | F37: =case!E95 -> 18204611 | G37: =case!F95 -> 14795011 | H37: =case!G95 -> 9311398 | I37: =case!H95 -> 6455031 | J37: =case!I95 -> 6151737
B38: Differenza tra totale attivo e totale attivo AIDA | C38: =C37-C35 -> 0 | D38: =D37-D35 -> 0 | E38: =E37-E35 -> 0 | F38: =F37-F35 -> 0 | G38: =G37-G35 -> 0 | H38: =H37-H35 -> 0 | I38: =I37-I35 -> 0 | J38: =J37-J35 -> 0
B39: Somma voci spostate nel passivo | C39: =case!B2+case!B46 -> 0 | D39: =case!C2+case!C46 -> 0 | E39: =case!D2+case!D46 -> 0 | F39: =case!E2+case!E46 -> 0 | G39: =case!F2+case!F46 -> 0 | H39: =case!G2+case!G46 -> 0 | I39: =case!H2+case!H46 -> 0 | J39: =case!I2+case!I46 -> 0
B40: Sbilancio | C40: =C38+C39 -> 0 | D40: =D38+D39 -> 0 | E40: =E38+E39 -> 0 | F40: =F38+F39 -> 0 | G40: =G38+G39 -> 0 | H40: =H38+H39 -> 0 | I40: =I38+I39 -> 0 | J40: =J38+J39 -> 0
B45: Stato Patrimoniale Passivo | C45: =C2 -> 31/12/2024 | D45: =D2 -> 31/12/2023 | E45: =E2 -> 31/12/2022 | F45: =F2 -> 31/12/2021 | G45: =G2 -> 31/12/2020 | H45: =H2 -> 31/12/2019 | I45: =I2 -> 31/12/2018 | J45: =J2 -> 31/12/2017
B46: Passività operative
B47: Passività operative correnti | C47: =SUMIF(case!$L:$L,$B47,case!B:B) -> 0 | D47: =SUMIF(case!$L:$L,$B47,case!C:C) -> 0 | E47: =SUMIF(case!$L:$L,$B47,case!D:D) -> 0 | F47: =SUMIF(case!$L:$L,$B47,case!E:E) -> 0 | G47: =SUMIF(case!$L:$L,$B47,case!F:F) -> 0 | H47: =SUMIF(case!$L:$L,$B47,case!G:G) -> 0 | I47: =SUMIF(case!$L:$L,$B47,case!H:H) -> 0 | J47: =SUMIF(case!$L:$L,$B47,case!I:I) -> 0
B48: Debiti vs fornitori | C48: =SUMIF(case!$L:$L,$B48,case!B:B) -> 2274193 | D48: =SUMIF(case!$L:$L,$B48,case!C:C) -> 2343088 | E48: =SUMIF(case!$L:$L,$B48,case!D:D) -> 2517619 | F48: =SUMIF(case!$L:$L,$B48,case!E:E) -> 2142223 | G48: =SUMIF(case!$L:$L,$B48,case!F:F) -> 1385728 | H48: =SUMIF(case!$L:$L,$B48,case!G:G) -> 2083244 | I48: =SUMIF(case!$L:$L,$B48,case!H:H) -> 1195746 | J48: =SUMIF(case!$L:$L,$B48,case!I:I) -> 1264218
B49: Debiti vs dipendenti | C49: =SUMIF(case!$L:$L,$B49,case!B:B) -> 0 | D49: =SUMIF(case!$L:$L,$B49,case!C:C) -> 0 | E49: =SUMIF(case!$L:$L,$B49,case!D:D) -> 0 | F49: =SUMIF(case!$L:$L,$B49,case!E:E) -> 0 | G49: =SUMIF(case!$L:$L,$B49,case!F:F) -> 0 | H49: =SUMIF(case!$L:$L,$B49,case!G:G) -> 0 | I49: =SUMIF(case!$L:$L,$B49,case!H:H) -> 0 | J49: =SUMIF(case!$L:$L,$B49,case!I:I) -> 0
B50: Altre passività operative correnti | C50: =SUMIF(case!$L:$L,$B50,case!B:B) -> 1755910 | D50: =SUMIF(case!$L:$L,$B50,case!C:C) -> 1902846 | E50: =SUMIF(case!$L:$L,$B50,case!D:D) -> 1988017 | F50: =SUMIF(case!$L:$L,$B50,case!E:E) -> 743242 | G50: =SUMIF(case!$L:$L,$B50,case!F:F) -> 648237 | H50: =SUMIF(case!$L:$L,$B50,case!G:G) -> 547878 | I50: =SUMIF(case!$L:$L,$B50,case!H:H) -> 447728 | J50: =SUMIF(case!$L:$L,$B50,case!I:I) -> 399886
B51: Totale passività operative correnti | C51: =SUM(C48:C50) -> 4030103 | D51: =SUM(D48:D50) -> 4245934 | E51: =SUM(E48:E50) -> 4505636 | F51: =SUM(F48:F50) -> 2885465 | G51: =SUM(G48:G50) -> 2033965 | H51: =SUM(H48:H50) -> 2631122 | I51: =SUM(I48:I50) -> 1643474 | J51: =SUM(J48:J50) -> 1664104
B52: Passività operative consolidate | C52: =SUMIF(case!$L:$L,$B52,case!B:B) -> 0 | D52: =SUMIF(case!$L:$L,$B52,case!C:C) -> 0 | E52: =SUMIF(case!$L:$L,$B52,case!D:D) -> 0 | F52: =SUMIF(case!$L:$L,$B52,case!E:E) -> 0 | G52: =SUMIF(case!$L:$L,$B52,case!F:F) -> 0 | H52: =SUMIF(case!$L:$L,$B52,case!G:G) -> 0 | I52: =SUMIF(case!$L:$L,$B52,case!H:H) -> 0 | J52: =SUMIF(case!$L:$L,$B52,case!I:I) -> 0
B53: Fondo TFR | C53: =SUMIF(case!$L:$L,$B53,case!B:B) -> 191675 | D53: =SUMIF(case!$L:$L,$B53,case!C:C) -> 179286 | E53: =SUMIF(case!$L:$L,$B53,case!D:D) -> 189098 | F53: =SUMIF(case!$L:$L,$B53,case!E:E) -> 197380 | G53: =SUMIF(case!$L:$L,$B53,case!F:F) -> 174392 | H53: =SUMIF(case!$L:$L,$B53,case!G:G) -> 206556 | I53: =SUMIF(case!$L:$L,$B53,case!H:H) -> 187238 | J53: =SUMIF(case!$L:$L,$B53,case!I:I) -> 173667
B54: Altre passività operative consolidate | C54: =SUMIF(case!$L:$L,$B54,case!B:B) -> 0 | D54: =SUMIF(case!$L:$L,$B54,case!C:C) -> 0 | E54: =SUMIF(case!$L:$L,$B54,case!D:D) -> 0 | F54: =SUMIF(case!$L:$L,$B54,case!E:E) -> 0 | G54: =SUMIF(case!$L:$L,$B54,case!F:F) -> 0 | H54: =SUMIF(case!$L:$L,$B54,case!G:G) -> 0 | I54: =SUMIF(case!$L:$L,$B54,case!H:H) -> 0 | J54: =SUMIF(case!$L:$L,$B54,case!I:I) -> 0
B55: Totale passività operative consolidate | C55: =SUM(C53:C54) -> 191675 | D55: =SUM(D53:D54) -> 179286 | E55: =SUM(E53:E54) -> 189098 | F55: =SUM(F53:F54) -> 197380 | G55: =SUM(G53:G54) -> 174392 | H55: =SUM(H53:H54) -> 206556 | I55: =SUM(I53:I54) -> 187238 | J55: =SUM(J53:J54) -> 173667
B56: Totale passività operative | C56: =C51+C55 -> 4221778 | D56: =D51+D55 -> 4425220 | E56: =E51+E55 -> 4694734 | F56: =F51+F55 -> 3082845 | G56: =G51+G55 -> 2208357 | H56: =H51+H55 -> 2837678 | I56: =I51+I55 -> 1830712 | J56: =J51+J55 -> 1837771
B58: Passività fiscali e fondi
B59: Debiti fisco previdenziali | C59: =SUMIF(case!$L:$L,$B59,case!B:B) -> 305861 | D59: =SUMIF(case!$L:$L,$B59,case!C:C) -> 221774 | E59: =SUMIF(case!$L:$L,$B59,case!D:D) -> 130071 | F59: =SUMIF(case!$L:$L,$B59,case!E:E) -> 171771 | G59: =SUMIF(case!$L:$L,$B59,case!F:F) -> 152360 | H59: =SUMIF(case!$L:$L,$B59,case!G:G) -> 109971 | I59: =SUMIF(case!$L:$L,$B59,case!H:H) -> 216414 | J59: =SUMIF(case!$L:$L,$B59,case!I:I) -> 303692
B60: Passività per imposte differite | C60: =SUMIF(case!$L:$L,$B60,case!B:B) -> 0 | D60: =SUMIF(case!$L:$L,$B60,case!C:C) -> 0 | E60: =SUMIF(case!$L:$L,$B60,case!D:D) -> 0 | F60: =SUMIF(case!$L:$L,$B60,case!E:E) -> 0 | G60: =SUMIF(case!$L:$L,$B60,case!F:F) -> 0 | H60: =SUMIF(case!$L:$L,$B60,case!G:G) -> 0 | I60: =SUMIF(case!$L:$L,$B60,case!H:H) -> 0 | J60: =SUMIF(case!$L:$L,$B60,case!I:I) -> 0
B61: Altri fondi | C61: =SUMIF(case!$L:$L,$B61,case!B:B) -> 0 | D61: =SUMIF(case!$L:$L,$B61,case!C:C) -> 0 | E61: =SUMIF(case!$L:$L,$B61,case!D:D) -> 0 | F61: =SUMIF(case!$L:$L,$B61,case!E:E) -> 0 | G61: =SUMIF(case!$L:$L,$B61,case!F:F) -> 0 | H61: =SUMIF(case!$L:$L,$B61,case!G:G) -> 0 | I61: =SUMIF(case!$L:$L,$B61,case!H:H) -> 41042 | J61: =SUMIF(case!$L:$L,$B61,case!I:I) -> 41042
B62: Totale passività fiscali e fondi | C62: =SUM(C59:C61) -> 305861 | D62: =SUM(D59:D61) -> 221774 | E62: =SUM(E59:E61) -> 130071 | F62: =SUM(F59:F61) -> 171771 | G62: =SUM(G59:G61) -> 152360 | H62: =SUM(H59:H61) -> 109971 | I62: =SUM(I59:I61) -> 257456 | J62: =SUM(J59:J61) -> 344734
B64: Passività accessorie
B65: Debiti verso controllate e collegate | C65: =SUMIF(case!$L:$L,$B65,case!B:B) -> 0 | D65: =SUMIF(case!$L:$L,$B65,case!C:C) -> 0 | E65: =SUMIF(case!$L:$L,$B65,case!D:D) -> 0 | F65: =SUMIF(case!$L:$L,$B65,case!E:E) -> 0 | G65: =SUMIF(case!$L:$L,$B65,case!F:F) -> 0 | H65: =SUMIF(case!$L:$L,$B65,case!G:G) -> 0 | I65: =SUMIF(case!$L:$L,$B65,case!H:H) -> 0 | J65: =SUMIF(case!$L:$L,$B65,case!I:I) -> 0
B66: Totale passività accessorie | C66: =C65 -> 0 | D66: =D65 -> 0 | E66: =E65 -> 0 | F66: =F65 -> 0 | G66: =G65 -> 0 | H66: =H65 -> 0 | I66: =I65 -> 0 | J66: =J65 -> 0
B68: Passività finanziarie
B69: Debiti strutturali a m/l termine | C69: =SUMIF(case!$L:$L,$B69,case!B:B) -> 5110204 | D69: =SUMIF(case!$L:$L,$B69,case!C:C) -> 6691873 | E69: =SUMIF(case!$L:$L,$B69,case!D:D) -> 6717513 | F69: =SUMIF(case!$L:$L,$B69,case!E:E) -> 7372195 | G69: =SUMIF(case!$L:$L,$B69,case!F:F) -> 6304053 | H69: =SUMIF(case!$L:$L,$B69,case!G:G) -> 588287 | I69: =SUMIF(case!$L:$L,$B69,case!H:H) -> 808395 | J69: =SUMIF(case!$L:$L,$B69,case!I:I) -> 952264
B70: Debiti strutturali a breve termine | C70: =SUMIF(case!$L:$L,$B70,case!B:B) -> 3395729 | D70: =SUMIF(case!$L:$L,$B70,case!C:C) -> 3987958 | E70: =SUMIF(case!$L:$L,$B70,case!D:D) -> 4519855 | F70: =SUMIF(case!$L:$L,$B70,case!E:E) -> 3495497 | G70: =SUMIF(case!$L:$L,$B70,case!F:F) -> 2924240 | H70: =SUMIF(case!$L:$L,$B70,case!G:G) -> 3390744 | I70: =SUMIF(case!$L:$L,$B70,case!H:H) -> 1825387 | J70: =SUMIF(case!$L:$L,$B70,case!I:I) -> 1954310
B71: Debiti di tesoreria | C71: =SUMIF(case!$L:$L,$B71,case!B:B) -> 0 | D71: =SUMIF(case!$L:$L,$B71,case!C:C) -> 0 | E71: =SUMIF(case!$L:$L,$B71,case!D:D) -> 0 | F71: =SUMIF(case!$L:$L,$B71,case!E:E) -> 0 | G71: =SUMIF(case!$L:$L,$B71,case!F:F) -> 0 | H71: =SUMIF(case!$L:$L,$B71,case!G:G) -> 0 | I71: =SUMIF(case!$L:$L,$B71,case!H:H) -> 0 | J71: =SUMIF(case!$L:$L,$B71,case!I:I) -> 0
B72: Strumenti derivati passivi | C72: =SUMIF(case!$L:$L,$B72,case!B:B) -> 0 | D72: =SUMIF(case!$L:$L,$B72,case!C:C) -> 0 | E72: =SUMIF(case!$L:$L,$B72,case!D:D) -> 0 | F72: =SUMIF(case!$L:$L,$B72,case!E:E) -> 0 | G72: =SUMIF(case!$L:$L,$B72,case!F:F) -> 0 | H72: =SUMIF(case!$L:$L,$B72,case!G:G) -> 0 | I72: =SUMIF(case!$L:$L,$B72,case!H:H) -> 0 | J72: =SUMIF(case!$L:$L,$B72,case!I:I) -> 0
B73: Totale passività finanziarie | C73: =SUM(C69:C72) -> 8505933 | D73: =SUM(D69:D72) -> 10679831 | E73: =SUM(E69:E72) -> 11237368 | F73: =SUM(F69:F72) -> 10867692 | G73: =SUM(G69:G72) -> 9228293 | H73: =SUM(H69:H72) -> 3979031 | I73: =SUM(I69:I72) -> 2633782 | J73: =SUM(J69:J72) -> 2906574
B75: Capitale proprio
B76: Finanziamenti netti vs soci e controllanti | C76: =SUMIF(case!$L:$L,$B76,case!B:B) -> 0 | D76: =SUMIF(case!$L:$L,$B76,case!C:C) -> 0 | E76: =SUMIF(case!$L:$L,$B76,case!D:D) -> 0 | F76: =SUMIF(case!$L:$L,$B76,case!E:E) -> 0 | G76: =SUMIF(case!$L:$L,$B76,case!F:F) -> 0 | H76: =SUMIF(case!$L:$L,$B76,case!G:G) -> 0 | I76: =SUMIF(case!$L:$L,$B76,case!H:H) -> 0 | J76: =SUMIF(case!$L:$L,$B76,case!I:I) -> 0
B77: Capitale netto | C77: =SUM(C78:C82) -> 5757287 | D77: =SUM(D78:D82) -> 5227552 | E77: =SUM(E78:E82) -> 4660887 | F77: =SUM(F78:F82) -> 4082303 | G77: =SUM(G78:G82) -> 3206001 | H77: =SUM(H78:H82) -> 2384718 | I77: =SUM(I78:I82) -> 1733081 | J77: =SUM(J78:J82) -> 1062658
B78: Capitale conferito dai soci | C78: =SUMIF(case!$L:$L,$B78,case!B:B) -> 140000 | D78: =SUMIF(case!$L:$L,$B78,case!C:C) -> 140000 | E78: =SUMIF(case!$L:$L,$B78,case!D:D) -> 140000 | F78: =SUMIF(case!$L:$L,$B78,case!E:E) -> 140000 | G78: =SUMIF(case!$L:$L,$B78,case!F:F) -> 140000 | H78: =SUMIF(case!$L:$L,$B78,case!G:G) -> 140000 | I78: =SUMIF(case!$L:$L,$B78,case!H:H) -> 140000 | J78: =SUMIF(case!$L:$L,$B78,case!I:I) -> 140000
B79: Utili non distribuiti | C79: =SUMIF(case!$L:$L,$B79,case!B:B) -> 4717554 | D79: =SUMIF(case!$L:$L,$B79,case!C:C) -> 4520885 | E79: =SUMIF(case!$L:$L,$B79,case!D:D) -> 3842306 | F79: =SUMIF(case!$L:$L,$B79,case!E:E) -> 2981000 | G79: =SUMIF(case!$L:$L,$B79,case!F:F) -> 2144719 | H79: =SUMIF(case!$L:$L,$B79,case!G:G) -> 1493082 | I79: =SUMIF(case!$L:$L,$B79,case!H:H) -> 922656 | J79: =SUMIF(case!$L:$L,$B79,case!I:I) -> 557912
B80: Riserve da rivalutazione | C80: =SUMIF(case!$L:$L,$B80,case!B:B) -> 0 | D80: =SUMIF(case!$L:$L,$B80,case!C:C) -> 0 | E80: =SUMIF(case!$L:$L,$B80,case!D:D) -> 0 | F80: =SUMIF(case!$L:$L,$B80,case!E:E) -> 0 | G80: =SUMIF(case!$L:$L,$B80,case!F:F) -> 0 | H80: =SUMIF(case!$L:$L,$B80,case!G:G) -> 0 | I80: =SUMIF(case!$L:$L,$B80,case!H:H) -> 0 | J80: =SUMIF(case!$L:$L,$B80,case!I:I) -> 0
B81: Azioni proprie e partecipazioni in controllanti | C81: =SUMIF(case!$L:$L,$B81,case!B:B) -> 0 | D81: =SUMIF(case!$L:$L,$B81,case!C:C) -> 0 | E81: =SUMIF(case!$L:$L,$B81,case!D:D) -> 0 | F81: =SUMIF(case!$L:$L,$B81,case!E:E) -> 0 | G81: =SUMIF(case!$L:$L,$B81,case!F:F) -> 0 | H81: =SUMIF(case!$L:$L,$B81,case!G:G) -> 0 | I81: =SUMIF(case!$L:$L,$B81,case!H:H) -> 0 | J81: =SUMIF(case!$L:$L,$B81,case!I:I) -> 0
B82: Reddito dell’esercizio | C82: =SUMIF(case!$L:$L,$B82,case!B:B) -> 899733 | D82: =SUMIF(case!$L:$L,$B82,case!C:C) -> 566667 | E82: =SUMIF(case!$L:$L,$B82,case!D:D) -> 678581 | F82: =SUMIF(case!$L:$L,$B82,case!E:E) -> 961303 | G82: =SUMIF(case!$L:$L,$B82,case!F:F) -> 921282 | H82: =SUMIF(case!$L:$L,$B82,case!G:G) -> 751636 | I82: =SUMIF(case!$L:$L,$B82,case!H:H) -> 670425 | J82: =SUMIF(case!$L:$L,$B82,case!I:I) -> 364746
B83: Capitale proprio di pertinenza di terzi | C83: =SUMIF(case!$L:$L,$B83,case!B:B) -> 0 | D83: =SUMIF(case!$L:$L,$B83,case!C:C) -> 0 | E83: =SUMIF(case!$L:$L,$B83,case!D:D) -> 0 | F83: =SUMIF(case!$L:$L,$B83,case!E:E) -> 0 | G83: =SUMIF(case!$L:$L,$B83,case!F:F) -> 0 | H83: =SUMIF(case!$L:$L,$B83,case!G:G) -> 0 | I83: =SUMIF(case!$L:$L,$B83,case!H:H) -> 0 | J83: =SUMIF(case!$L:$L,$B83,case!I:I) -> 0
B84: Totale capitale proprio | C84: =C76+C77+C83 -> 5757287 | D84: =D76+D77+D83 -> 5227552 | E84: =E76+E77+E83 -> 4660887 | F84: =F76+F77+F83 -> 4082303 | G84: =G76+G77+G83 -> 3206001 | H84: =H76+H77+H83 -> 2384718 | I84: =I76+I77+I83 -> 1733081 | J84: =J76+J77+J83 -> 1062658
B86: Totale passivo | C86: =C56+C62+C66+C73+C84 -> 18790859 | D86: =D56+D62+D66+D73+D84 -> 20554377 | E86: =E56+E62+E66+E73+E84 -> 20723060 | F86: =F56+F62+F66+F73+F84 -> 18204611 | G86: =G56+G62+G66+G73+G84 -> 14795011 | H86: =H56+H62+H66+H73+H84 -> 9311398 | I86: =I56+I62+I66+I73+I84 -> 6455031 | J86: =J56+J62+J66+J73+J84 -> 6151737
B88: Check con totale attivo AIDA | C88: =case!B168 -> 18790859 | D88: =case!C168 -> 20554377 | E88: =case!D168 -> 20723060 | F88: =case!E168 -> 18204611 | G88: =case!F168 -> 14795011 | H88: =case!G168 -> 9311398 | I88: =case!H168 -> 6455031 | J88: =case!I168 -> 6151737
B89: diff da AIDA | C89: =C88-C86 -> 0 | D89: =D88-D86 -> 0 | E89: =E88-E86 -> 0 | F89: =F88-F86 -> 0 | G89: =G88-G86 -> 0 | H89: =H88-H86 -> 0 | I89: =I88-I86 -> 0 | J89: =J88-J86 -> 0
B90: Check Tot.Attivo - Tot.Passivo | C90: =C35-C86 -> 0 | D90: =D35-D86 -> 0 | E90: =E35-E86 -> 0 | F90: =F35-F86 -> 0 | G90: =G35-G86 -> 0 | H90: =H35-H86 -> 0 | I90: =I35-I86 -> 0 | J90: =J35-J86 -> 0
B92: Relazione fondamentale fonti/impieghi:
B93: Attività Operative Nette Estese (AON*) | C93: =C16-C56+C21-C62 -> 13962088 | D93: =D16-D56+D21-D62 -> 14957139 | E93: =E16-E56+E21-E62 -> 14682021 | F93: =F16-F56+F21-F62 -> 12621622 | G93: =G16-G56+G21-G62 -> 10439151 | H93: =H16-H56+H21-H62 -> 5753308 | I93: =I16-I56+I21-I62 -> 4023273 | J93: =J16-J56+J21-J62 -> 3249932
B94: Attività Accessorie Nette (AACCN) | C94: =C27-C66 -> 58702 | D94: =D27-D66 -> 58702 | E94: =E27-E66 -> 58702 | F94: =F27-F66 -> 58702 | G94: =G27-G66 -> 6512 | H94: =H27-H66 -> 6512 | I94: =I27-I66 -> 6512 | J94: =J27-J66 -> 6512
B95: Posizione Finanziaria Netta (+Liquidità - Debito) | C95: =C33-C73 -> -8263503 | D95: =D33-D73 -> -9788289 | E95: =E33-E73 -> -10079836 | F95: =F33-F73 -> -8598021 | G95: =G33-G73 -> -7239662 | H95: =H33-H73 -> -3375102 | I95: =I33-I73 -> -2296704 | J95: =J33-J73 -> -2193786
B96: Capitale Proprio | C96: =C84 -> 5757287 | D96: =D84 -> 5227552 | E96: =E84 -> 4660887 | F96: =F84 -> 4082303 | G96: =G84 -> 3206001 | H96: =H84 -> 2384718 | I96: =I84 -> 1733081 | J96: =J84 -> 1062658
B97: Totale Attivo | C97: =C35 -> 18790859 | D97: =D35 -> 20554377 | E97: =E35 -> 20723060 | F97: =F35 -> 18204611 | G97: =G35 -> 14795011 | H97: =H35 -> 9311398 | I97: =I35 -> 6455031 | J97: =J35 -> 6151737
B98: Totale Passivo | C98: =C86 -> 18790859 | D98: =D86 -> 20554377 | E98: =E86 -> 20723060 | F98: =F86 -> 18204611 | G98: =G86 -> 14795011 | H98: =H86 -> 9311398 | I98: =I86 -> 6455031 | J98: =J86 -> 6151737
B99: Sbilancio | C99: =C97-C98 -> 0 | D99: =D97-D98 -> 0 | E99: =E97-E98 -> 0 | F99: =F97-F98 -> 0 | G99: =G97-G98 -> 0 | H99: =H97-H98 -> 0 | I99: =I97-I98 -> 0 | J99: =J97-J98 -> 0
B101: CCON | C101: =C8-C51 -> 5652102 | D101: =D8-D51 -> 6091068 | E101: =E8-E51 -> 4739282 | F101: =F8-F51 -> 3336501 | G101: =G8-G51 -> 3414534 | H101: =H8-H51 -> 3284267 | I101: =I8-I51 -> 3215402 | J101: =J8-J51 -> 2861588
B102: AON -> | C102: =C16-C56 -> 14244675 | D102: =D16-D56 -> 15035932 | E102: =E16-E56 -> 14106429 | F102: =F16-F56 -> 12646121 | G102: =G16-G56 -> 10306811 | H102: =H16-H56 -> 5687488 | I102: =I16-I56 -> 4222775 | J102: =J16-J56 -> 3589908
B103: debito netto, se neg è liq netta -> | C103: =-C95 -> 8263503 | D103: =-D95 -> 9788289 | E103: =-E95 -> 10079836 | F103: =-F95 -> 8598021 | G103: =-G95 -> 7239662 | H103: =-H95 -> 3375102 | I103: =-I95 -> 2296704 | J103: =-J95 -> 2193786
B104: AON*+ att.gestione accessoria | C104: =C93+C94 -> 14020790 | D104: =D93+D94 -> 15015841 | E104: =E93+E94 -> 14740723 | F104: =F93+F94 -> 12680324 | G104: =G93+G94 -> 10445663 | H104: =H93+H94 -> 5759820 | I104: =I93+I94 -> 4029785 | J104: =J93+J94 -> 3256444
B105: capitale proprio + debito netto | C105: =C96+C103 -> 14020790 | D105: =D96+D103 -> 15015841 | E105: =E96+E103 -> 14740723 | F105: =F96+F103 -> 12680324 | G105: =G96+G103 -> 10445663 | H105: =H96+H103 -> 5759820 | I105: =I96+I103 -> 4029785 | J105: =J96+J103 -> 3256444
B106: Relazione fonti/impieghi | C106: =C104-C105 -> 0 | D106: =D104-D105 -> 0 | E106: =E104-E105 -> 0 | F106: =F104-F105 -> 0 | G106: =G104-G105 -> 0 | H106: =H104-H105 -> 0 | I106: =I104-I105 -> 0 | J106: =J104-J105 -> 0
B109: Conto Economico | C109: =C2 -> 31/12/2024 | D109: =D2 -> 31/12/2023 | E109: =E2 -> 31/12/2022 | F109: =F2 -> 31/12/2021 | G109: =G2 -> 31/12/2020 | H109: =H2 -> 31/12/2019 | I109: =I2 -> 31/12/2018 | J109: =J2 -> 31/12/2017
B110: Gestione operativa
B111: (A) Ricavi di vendita | C111: =SUMIF(case!$L:$L,$B111,case!B:B)-C127 -> 21650995 | D111: =SUMIF(case!$L:$L,$B111,case!C:C)-D127 -> 21142391 | E111: =SUMIF(case!$L:$L,$B111,case!D:D)-E127 -> 17821289 | F111: =SUMIF(case!$L:$L,$B111,case!E:E)-F127 -> 15638358 | G111: =SUMIF(case!$L:$L,$B111,case!F:F)-G127 -> 14336879 | H111: =SUMIF(case!$L:$L,$B111,case!G:G)-H127 -> 13550152 | I111: =SUMIF(case!$L:$L,$B111,case!H:H)-I127 -> 11519434 | J111: =SUMIF(case!$L:$L,$B111,case!I:I)-J127 -> 9917341
B112: Acquisti
B113: − Materie prime e merci | C113: =SUMIF(case!$L:$L,$B113,case!B:B) -> -14699595 | D113: =SUMIF(case!$L:$L,$B113,case!C:C) -> -14953922 | E113: =SUMIF(case!$L:$L,$B113,case!D:D) -> -13825249 | F113: =SUMIF(case!$L:$L,$B113,case!E:E) -> -10511247 | G113: =SUMIF(case!$L:$L,$B113,case!F:F) -> -9060210 | H113: =SUMIF(case!$L:$L,$B113,case!G:G) -> -9472095 | I113: =SUMIF(case!$L:$L,$B113,case!H:H) -> -7620373 | J113: =SUMIF(case!$L:$L,$B113,case!I:I) -> -6509298
B114: − Servizi | C114: =SUMIF(case!$L:$L,$B114,case!B:B) -> -2422226 | D114: =SUMIF(case!$L:$L,$B114,case!C:C) -> -2512120 | E114: =SUMIF(case!$L:$L,$B114,case!D:D) -> -2928006 | F114: =SUMIF(case!$L:$L,$B114,case!E:E) -> -2010409 | G114: =SUMIF(case!$L:$L,$B114,case!F:F) -> -1917407 | H114: =SUMIF(case!$L:$L,$B114,case!G:G) -> -1966664 | I114: =SUMIF(case!$L:$L,$B114,case!H:H) -> -1696231 | J114: =SUMIF(case!$L:$L,$B114,case!I:I) -> -1342031
B115: − Godimento beni di terzi | C115: =SUMIF(case!$L:$L,$B115,case!B:B) -> -117380 | D115: =SUMIF(case!$L:$L,$B115,case!C:C) -> -75105 | E115: =SUMIF(case!$L:$L,$B115,case!D:D) -> -85474 | F115: =SUMIF(case!$L:$L,$B115,case!E:E) -> -78590 | G115: =SUMIF(case!$L:$L,$B115,case!F:F) -> -73502 | H115: =SUMIF(case!$L:$L,$B115,case!G:G) -> -66140 | I115: =SUMIF(case!$L:$L,$B115,case!H:H) -> -53268 | J115: =SUMIF(case!$L:$L,$B115,case!I:I) -> -64128
B116: = − Totale acquisti MP, merci e servizi | C116: =SUM(C113:C115) -> -17239201 | D116: =SUM(D113:D115) -> -17541147 | E116: =SUM(E113:E115) -> -16838729 | F116: =SUM(F113:F115) -> -12600246 | G116: =SUM(G113:G115) -> -11051119 | H116: =SUM(H113:H115) -> -11504899 | I116: =SUM(I113:I115) -> -9369872 | J116: =SUM(J113:J115) -> -7915457
B117: + Variazione rimanenze di MP e merci | C117: =SUMIF(case!$L:$L,$B117,case!B:B) -> 141939 | D117: =SUMIF(case!$L:$L,$B117,case!C:C) -> -135450 | E117: =SUMIF(case!$L:$L,$B117,case!D:D) -> 162139 | F117: =SUMIF(case!$L:$L,$B117,case!E:E) -> 79592 | G117: =SUMIF(case!$L:$L,$B117,case!F:F) -> -76252 | H117: =SUMIF(case!$L:$L,$B117,case!G:G) -> 94059 | I117: =SUMIF(case!$L:$L,$B117,case!H:H) -> -35037 | J117: =SUMIF(case!$L:$L,$B117,case!I:I) -> 61620
B118: + Variazione rimanenze prodotti finiti e semilavorati | C118: =SUMIF(case!$L:$L,$B118,case!B:B) -> -573471 | D118: =SUMIF(case!$L:$L,$B118,case!C:C) -> -74468 | E118: =SUMIF(case!$L:$L,$B118,case!D:D) -> 2163754 | F118: =SUMIF(case!$L:$L,$B118,case!E:E) -> 288102 | G118: =SUMIF(case!$L:$L,$B118,case!F:F) -> -377792 | H118: =SUMIF(case!$L:$L,$B118,case!G:G) -> 494422 | I118: =SUMIF(case!$L:$L,$B118,case!H:H) -> 386643 | J118: =SUMIF(case!$L:$L,$B118,case!I:I) -> -75281
B119: + Variazione lavori in corso su ordinazione | C119: =SUMIF(case!$L:$L,$B119,case!B:B) -> 0 | D119: =SUMIF(case!$L:$L,$B119,case!C:C) -> 0 | E119: =SUMIF(case!$L:$L,$B119,case!D:D) -> 0 | F119: =SUMIF(case!$L:$L,$B119,case!E:E) -> 0 | G119: =SUMIF(case!$L:$L,$B119,case!F:F) -> 0 | H119: =SUMIF(case!$L:$L,$B119,case!G:G) -> 0 | I119: =SUMIF(case!$L:$L,$B119,case!H:H) -> 0 | J119: =SUMIF(case!$L:$L,$B119,case!I:I) -> 0
B120: = (B) − Costo della produzione venduta | C120: =C116+C117+C118+C119 -> -17670733 | D120: =D116+D117+D118+D119 -> -17751065 | E120: =E116+E117+E118+E119 -> -14512836 | F120: =F116+F117+F118+F119 -> -12232552 | G120: =G116+G117+G118+G119 -> -11505163 | H120: =H116+H117+H118+H119 -> -10916418 | I120: =I116+I117+I118+I119 -> -9018266 | J120: =J116+J117+J118+J119 -> -7929118
...

Sheet RF
B1: Rendiconto finanziario | C1: =case!B1 -> 31/12/2024 | D1: =case!C1 -> 31/12/2023 | E1: =case!D1 -> 31/12/2022 | F1: =case!E1 -> 31/12/2021 | G1: =case!F1 -> 31/12/2020 | H1: =case!G1 -> 31/12/2019 | I1: =case!H1 -> 31/12/2018 | J1: =case!I1 -> 31/12/2017
B2: Flussi di cassa della gestione operativa e accessoria
B3: Flussi di cassa della gestione operativa corrente
A4: + | B4: Reddito operativo | C4: ='RC'!C131 -> 1588849 | D4: ='RC'!D131 -> 1117327 | E4: ='RC'!E131 -> 963975 | F4: ='RC'!F131 -> 1411257 | G4: ='RC'!G131 -> 1351726 | H4: ='RC'!H131 -> 1069627 | I4: ='RC'!I131 -> 1052950 | J4: ='RC'!J131 -> 635847
A5: ± | B5: Reddito gestioni accessoria e straordinaria | C5: ='RC'!C146 -> 0 | D5: ='RC'!D146 -> 0 | E5: ='RC'!E146 -> 0 | F5: ='RC'!F146 -> 0 | G5: ='RC'!G146 -> 0 | H5: ='RC'!H146 -> 0 | I5: ='RC'!I146 -> 0 | J5: ='RC'!J146 -> 0
A6: + | B6: Riaggiunta ammortamenti | C6: =-'RC'!C124 -> 916802 | D6: =-'RC'!D124 -> 899828 | E6: =-'RC'!E124 -> 856051 | F6: =-'RC'!F124 -> 470290 | G6: =-'RC'!G124 -> 171279 | H6: =-'RC'!H124 -> 180598 | I6: =-'RC'!I124 -> 184962 | J6: =-'RC'!J124 -> 215317
A7: - | B7: (Imposte + Risparmio fiscale interessi netti) | C7: =-('RC'!C149+'RC'!C157) -> 100967.94 | D7: =-('RC'!D149+'RC'!D157) -> 2676.0664 | E7: =-('RC'!E149+'RC'!E157) -> 20538.049 | F7: =-('RC'!F149+'RC'!F157) -> 201174.49 | G7: =-('RC'!G149+'RC'!G157) -> 235308.93 | H7: =-('RC'!H149+'RC'!H157) -> 196885.32 | I7: =-('RC'!I149+'RC'!I157) -> 250659.96 | J7: =-('RC'!J149+'RC'!J157) -> 136307.83
A8: = | B8: EBITDA al netto delle imposte | C8: =C4+C5+C6-C7 -> 2404683.1 | D8: =D4+D5+D6-D7 -> 2014478.9 | E8: =E4+E5+E6-E7 -> 1799488 | F8: =F4+F5+F6-F7 -> 1680372.5 | G8: =G4+G5+G6-G7 -> 1287696.1 | H8: =H4+H5+H6-H7 -> 1053339.7 | I8: =I4+I5+I6-I7 -> 987252.04 | J8: =J4+J5+J6-J7 -> 714856.17
B9: Rettifiche per determinare il flusso di cassa
B10: Variazione del CCON*
A11: - | B11: (Aumento) diminuzione crediti verso clienti | C11: =-'RC'!C5 -> -4256399 | D11: =-'RC'!D5 -> -3896776 | E11: =-'RC'!E5 -> -2966203 | F11: =-'RC'!F5 -> -3180616 | G11: =-'RC'!G5 -> -2787212 | H11: =-'RC'!H5 -> -2642901 | I11: =-'RC'!I5 -> -2353521 | J11: =-'RC'!J5 -> -2381302
A12: - | B12: (Aumento) diminuzione scorte magazzino | C12: =-'RC'!C6 -> -4608814 | D12: =-'RC'!D6 -> -5040346 | E12: =-'RC'!E6 -> -5250264 | F12: =-'RC'!F6 -> -2924371 | G12: =-'RC'!G6 -> -2556678 | H12: =-'RC'!H6 -> -3010721 | I12: =-'RC'!I6 -> -2422241 | J12: =-'RC'!J6 -> -2070635
A13: - | B13: (Aumento) diminuzione altre attività correnti | C13: =-'RC'!C7 -> -816992 | D13: =-'RC'!D7 -> -1399880 | E13: =-'RC'!E7 -> -1028451 | F13: =-'RC'!F7 -> -116979 | G13: =-'RC'!G7 -> -104609 | H13: =-'RC'!H7 -> -261767 | I13: =-'RC'!I7 -> -83114 | J13: =-'RC'!J7 -> -73755
A14: + | B14: Aumento (diminuzione) debiti verso fornitori | C14: ='RC'!C48 -> 2274193 | D14: ='RC'!D48 -> 2343088 | E14: ='RC'!E48 -> 2517619 | F14: ='RC'!F48 -> 2142223 | G14: ='RC'!G48 -> 1385728 | H14: ='RC'!H48 -> 2083244 | I14: ='RC'!I48 -> 1195746 | J14: ='RC'!J48 -> 1264218
A15: + | B15: Aumento (diminuzione) altre passività correnti | C15: ='RC'!C50 -> 1755910 | D15: ='RC'!D50 -> 1902846 | E15: ='RC'!E50 -> 1988017 | F15: ='RC'!F50 -> 743242 | G15: ='RC'!G50 -> 648237 | H15: ='RC'!H50 -> 547878 | I15: ='RC'!I50 -> 447728 | J15: ='RC'!J50 -> 399886
A16: - | B16: (Aumento) diminuzione attività fiscali | C16: =-'RC'!C21 -> -23274 | D16: =-'RC'!D21 -> -142981 | E16: =-'RC'!E21 -> -705663 | F16: =-'RC'!F21 -> -147272 | G16: =-'RC'!G21 -> -284700 | H16: =-'RC'!H21 -> -175791 | I16: =-'RC'!I21 -> -57954 | J16: =-'RC'!J21 -> -4758
A17: + | B17: Aumento (diminuzione) passività fiscali | C17: ='RC'!C62 -> 305861 | D17: ='RC'!D62 -> 221774 | E17: ='RC'!E62 -> 130071 | F17: ='RC'!F62 -> 171771 | G17: ='RC'!G62 -> 152360 | H17: ='RC'!H62 -> 109971 | I17: ='RC'!I62 -> 257456 | J17: ='RC'!J62 -> 344734
A18: = | B18: (Aumento) diminuzione CCON* | C18: =SUM(C11:C17) -> -5369515 | D18: =SUM(D11:D17) -> -6012275 | E18: =SUM(E11:E17) -> -5314874 | F18: =SUM(F11:F17) -> -3312002 | G18: =SUM(G11:G17) -> -3546874 | H18: =SUM(H11:H17) -> -3350087 | I18: =SUM(I11:I17) -> -3015900 | J18: =SUM(J11:J17) -> -2521612
A19: + | B19: Aumento (diminuzione) fondo TFR | C19: ='RC'!C53 -> 191675 | D19: ='RC'!D53 -> 179286 | E19: ='RC'!E53 -> 189098 | F19: ='RC'!F53 -> 197380 | G19: ='RC'!G53 -> 174392 | H19: ='RC'!H53 -> 206556 | I19: ='RC'!I53 -> 187238 | J19: ='RC'!J53 -> 173667
A20: - | B20: (Aumento) diminuzione altre attività operative immobilizzate | C20: =-'RC'!C15 -> 0 | D20: =-'RC'!D15 -> 0 | E20: =-'RC'!E15 -> 0 | F20: =-'RC'!F15 -> 0 | G20: =-'RC'!G15 -> -8192 | H20: =-'RC'!H15 -> -8192 | I20: =-'RC'!I15 -> -8192 | J20: =-'RC'!J15 -> -8192
A21: + | B21: Aumento (diminuzione) altre passività operative consolidate | C21: ='RC'!C54 -> 0 | D21: ='RC'!D54 -> 0 | E21: ='RC'!E54 -> 0 | F21: ='RC'!F54 -> 0 | G21: ='RC'!G54 -> 0 | H21: ='RC'!H54 -> 0 | I21: ='RC'!I54 -> 0 | J21: ='RC'!J54 -> 0
A22: = | B22: Totale rettifiche | C22: =SUM(C18:C21) -> -5177840 | D22: =SUM(D18:D21) -> -5832989 | E22: =SUM(E18:E21) -> -5125776 | F22: =SUM(F18:F21) -> -3114622 | G22: =SUM(G18:G21) -> -3380674 | H22: =SUM(H18:H21) -> -3151723 | I22: =SUM(I18:I21) -> -2836854 | J22: =SUM(J18:J21) -> -2356137
A23: = | B23: Flussi di cassa netti gestione operativa corrente, acc e straord. | C23: =C8+C22 -> -2773156.9 | D23: =D8+D22 -> -3818510.1 | E23: =E8+E22 -> -3326288 | F23: =F8+F22 -> -1434249.5 | G23: =G8+G22 -> -2092977.9 | H23: =H8+H22 -> -2098383.3 | I23: =I8+I22 -> -1849602 | J23: =J8+J22 -> -1641280.8
B24: Flussi di cassa della gestione investimenti | N24: 31/12/2021 | O24: 31/12/2022 | P24: 31/12/2023 | Q24: 31/12/2024
A25: - | B25: (Aumento) diminuzione Immobilizzazioni operative nette | C25: =-'RC'!C12 -> -8784248 | D25: =-'RC'!D12 -> -9124150 | E25: =-'RC'!E12 -> -9556245 | F25: =-'RC'!F12 -> -9507000 | G25: =-'RC'!G12 -> -7058477 | H25: =-'RC'!H12 -> -2601585 | I25: =-'RC'!I12 -> -1186419 | J25: =-'RC'!J12 -> -893795 | M25: FCFF | N25: =F31-G31 -> -2140995.6 | O25: =E31-F31 -> -2327044.6 | P25: =D31-E31 -> -103904.02 | Q25: =C31-D31 -> 1368281.1
A26: - | B26: (Aumento) diminuzione attività accessorie | C26: =-'RC'!C27 -> -58702 | D26: =-'RC'!D27 -> -58702 | E26: =-'RC'!E27 -> -58702 | F26: =-'RC'!F27 -> -58702 | G26: =-'RC'!G27 -> -6512 | H26: =-'RC'!H27 -> -6512 | I26: =-'RC'!I27 -> -6512 | J26: =-'RC'!J27 -> -6512 | M26: FCFE | N26: =F41-G41 -> -555241 | O26: =E41-F41 -> -1973445 | P26: =D41-E41 -> -944569 | Q26: =C41-D41 -> -845781
A27: + | B27: Aumento (diminuzione) debiti vs controllate e collegate | C27: ='RC'!C66 -> 0 | D27: ='RC'!D66 -> 0 | E27: ='RC'!E66 -> 0 | F27: ='RC'!F66 -> 0 | G27: ='RC'!G66 -> 0 | H27: ='RC'!H66 -> 0 | I27: ='RC'!I66 -> 0 | J27: ='RC'!J66 -> 0 | M27: FCCP | N27: =F48-G48 -> 836281 | O27: =E48-F48 -> 861306 | P27: =D48-E48 -> 678579 | Q27: =C48-D48 -> 196669
A28: - | B28: (Ammortamenti) | C28: ='RC'!C124 -> -916802 | D28: ='RC'!D124 -> -899828 | E28: ='RC'!E124 -> -856051 | F28: ='RC'!F124 -> -470290 | G28: ='RC'!G124 -> -171279 | H28: ='RC'!H124 -> -180598 | I28: ='RC'!I124 -> -184962 | J28: ='RC'!J124 -> -215317 | M28: NCF | N28: =N26+N27 -> 281040 | O28: =O27+O26 -> -1112139 | P28: =P26+P27 -> -265990 | Q28: =Q26+Q27 -> -649112
A29: + | B29: Aumento (diminuzione) riserve da rivalutazione | C29: ='RC'!C80 -> 0 | D29: ='RC'!D80 -> 0 | E29: ='RC'!E80 -> 0 | F29: ='RC'!F80 -> 0 | G29: ='RC'!G80 -> 0 | H29: ='RC'!H80 -> 0 | I29: ='RC'!I80 -> 0 | J29: ='RC'!J80 -> 0
A30: = | B30: Flussi di cassa netti della gestione investimenti | C30: =SUM(C25:C29) -> -9759752 | D30: =SUM(D25:D29) -> -10082680 | E30: =SUM(E25:E29) -> -10470998 | F30: =SUM(F25:F29) -> -10035992 | G30: =SUM(G25:G29) -> -7236268 | H30: =SUM(H25:H29) -> -2788695 | I30: =SUM(I25:I29) -> -1377893 | J30: =SUM(J25:J29) -> -1115624
A31: = | B31: Free cash flow to the firm (FCFF) | C31: =C23+C30 -> -12532909 | D31: =D23+D30 -> -13901190 | E31: =E23+E30 -> -13797286 | F31: =F23+F30 -> -11470241 | G31: =G23+G30 -> -9329245.9 | H31: =H23+H30 -> -4887078.3 | I31: =I23+I30 -> -3227495 | J31: =J23+J30 -> -2756904.8
B32: Flussi di cassa della gestione finanziaria
B33: Debito e attività finanziarie (esclusa tesoreria)
A34: - | B34: (Oneri finanziari netti) | C34: ='RC'!C140 -> -501648 | D34: ='RC'!D140 -> -526256 | E34: ='RC'!E140 -> -253466 | F34: ='RC'!F140 -> -207017 | G34: ='RC'!G140 -> -158955 | H34: ='RC'!H140 -> -98799 | I34: ='RC'!I140 -> -101816 | J34: ='RC'!J140 -> -102408
A35: + | B35: Risparmio fiscale interessi netti | C35: =-'RC'!C157 -> -86500.056 | D35: =-'RC'!D157 -> -21727.934 | E35: =-'RC'!E157 -> -11389.951 | F35: =-'RC'!F157 -> -41762.513 | G35: =-'RC'!G157 -> -36180.066 | H35: =-'RC'!H157 -> -22306.681 | I35: =-'RC'!I157 -> -30049.044 | J35: =-'RC'!J157 -> -32385.17
A36: + | B36: Strumenti derivati: (aumento) diminuzione attivi + aumento (diminuzione) passivi | C36: =-'RC'!C32+'RC'!C72 -> 0 | D36: =-'RC'!D32+'RC'!D72 -> 0 | E36: =-'RC'!E32+'RC'!E72 -> 0 | F36: =-'RC'!F32+'RC'!F72 -> 0 | G36: =-'RC'!G32+'RC'!G72 -> 0 | H36: =-'RC'!H32+'RC'!H72 -> 0 | I36: =-'RC'!I32+'RC'!I72 -> 0 | J36: =-'RC'!J32+'RC'!J72 -> 0
A37: + | B37: Aumento (diminuzione) debiti struttturali a medio-lungo | C37: ='RC'!C69 -> 5110204 | D37: ='RC'!D69 -> 6691873 | E37: ='RC'!E69 -> 6717513 | F37: ='RC'!F69 -> 7372195 | G37: ='RC'!G69 -> 6304053 | H37: ='RC'!H69 -> 588287 | I37: ='RC'!I69 -> 808395 | J37: ='RC'!J69 -> 952264
A38: + | B38: Aumento (diminuzione) debiti strutturali a breve | C38: ='RC'!C70 -> 3395729 | D38: ='RC'!D70 -> 3987958 | E38: ='RC'!E70 -> 4519855 | F38: ='RC'!F70 -> 3495497 | G38: ='RC'!G70 -> 2924240 | H38: ='RC'!H70 -> 3390744 | I38: ='RC'!I70 -> 1825387 | J38: ='RC'!J70 -> 1954310
A39: - | B39: (Aumento) diminuzione riserve strategiche di liquidità | C39: =-'RC'!C30 -> 0 | D39: =-'RC'!D30 -> 0 | E39: =-'RC'!E30 -> 0 | F39: =-'RC'!F30 -> 0 | G39: =-'RC'!G30 -> 0 | H39: =-'RC'!H30 -> 0 | I39: =-'RC'!I30 -> 0 | J39: =-'RC'!J30 -> 0
A40: = | B40: Flussi di cassa netti sul debito netto (esclusa tesoreria) (FCDN) | C40: =SUM(C34:C39) -> 7917784.9 | D40: =SUM(D34:D39) -> 10131847 | E40: =SUM(E34:E39) -> 10972512 | F40: =SUM(F34:F39) -> 10618912 | G40: =SUM(G34:G39) -> 9033157.9 | H40: =SUM(H34:H39) -> 3857925.3 | I40: =SUM(I34:I39) -> 2501917 | J40: =SUM(J34:J39) -> 2771780.8
A41: = | B41: Free cash flow to equity (FCFE) | C41: =C31+C40 -> -4615124 | D41: =D31+D40 -> -3769343 | E41: =E31+E40 -> -2824774 | F41: =F31+F40 -> -851329 | G41: =G31+G40 -> -296088 | H41: =H31+H40 -> -1029153 | I41: =I31+I40 -> -725578 | J41: =J31+J40 -> 14876
B42: Capitale proprio
A43: - | B43: (Stima utili distribuiti) | C43: ='RC'!C79 -> 4717554 | D43: ='RC'!D79 -> 4520885 | E43: ='RC'!E79 -> 3842306 | F43: ='RC'!F79 -> 2981000 | G43: ='RC'!G79 -> 2144719 | H43: ='RC'!H79 -> 1493082 | I43: ='RC'!I79 -> 922656 | J43: ='RC'!J79 -> 557912
A44: - | B44: (Aumento) diminuzione azioni proprie e partec in controllanti | C44: =-'RC'!C81 -> 0 | D44: =-'RC'!D81 -> 0 | E44: =-'RC'!E81 -> 0 | F44: =-'RC'!F81 -> 0 | G44: =-'RC'!G81 -> 0 | H44: =-'RC'!H81 -> 0 | I44: =-'RC'!I81 -> 0 | J44: =-'RC'!J81 -> 0
A45: + | B45: Aumento (diminuzione) finanziamenti netti da soci e controllanti | C45: ='RC'!C76 -> 0 | D45: ='RC'!D76 -> 0 | E45: ='RC'!E76 -> 0 | F45: ='RC'!F76 -> 0 | G45: ='RC'!G76 -> 0 | H45: ='RC'!H76 -> 0 | I45: ='RC'!I76 -> 0 | J45: ='RC'!J76 -> 0
A46: + | B46: Aumento (diminuzione) di capitale conferito dai soci | C46: ='RC'!C78 -> 140000 | D46: ='RC'!D78 -> 140000 | E46: ='RC'!E78 -> 140000 | F46: ='RC'!F78 -> 140000 | G46: ='RC'!G78 -> 140000 | H46: ='RC'!H78 -> 140000 | I46: ='RC'!I78 -> 140000 | J46: ='RC'!J78 -> 140000
A47: + | B47: Aumento (diminuzione) capitale proprio di pertinenza di terzi | C47: ='RC'!C83 -> 0 | D47: ='RC'!D83 -> 0 | E47: ='RC'!E83 -> 0 | F47: ='RC'!F83 -> 0 | G47: ='RC'!G83 -> 0 | H47: ='RC'!H83 -> 0 | I47: ='RC'!I83 -> 0 | J47: ='RC'!J83 -> 0
A48: = | B48: Flussi di cassa effettivi sul capitale proprio (FCCP) | C48: =SUM(C43:C47) -> 4857554 | D48: =SUM(D43:D47) -> 4660885 | E48: =SUM(E43:E47) -> 3982306 | F48: =SUM(F43:F47) -> 3121000 | G48: =SUM(G43:G47) -> 2284719 | H48: =SUM(H43:H47) -> 1633082 | I48: =SUM(I43:I47) -> 1062656 | J48: =SUM(J43:J47) -> 697912
A49: = | B49: Flusso di cassa netto (NCF) | C49: =C41+C48 -> 242430 | D49: =D41+D48 -> 891542 | E49: =E41+E48 -> 1157532 | F49: =F41+F48 -> 2269671 | G49: =G41+G48 -> 1988631 | H49: =H41+H48 -> 603929 | I49: =I41+I48 -> 337078 | J49: =J41+J48 -> 712788
B51: Check NCF
A52: + | B52: Aumento (diminuzione) attività di tesoreria | C52: ='RC'!C31 -> 242430 | D52: ='RC'!D31 -> 891542 | E52: ='RC'!E31 -> 1157532 | F52: ='RC'!F31 -> 2269671 | G52: ='RC'!G31 -> 1988631 | H52: ='RC'!H31 -> 603929 | I52: ='RC'!I31 -> 337078 | J52: ='RC'!J31 -> 712788
A53: - | B53: (Aumento) diminuzione debiti di tesoreria | C53: =-'RC'!C71 -> 0 | D53: =-'RC'!D71 -> 0 | E53: =-'RC'!E71 -> 0 | F53: =-'RC'!F71 -> 0 | G53: =-'RC'!G71 -> 0 | H53: =-'RC'!H71 -> 0 | I53: =-'RC'!I71 -> 0 | J53: =-'RC'!J71 -> 0
A54: = | B54: Variazione posizione netta di tesoreria | C54: =C52+C53 -> 242430 | D54: =D52+D53 -> 891542 | E54: =E52+E53 -> 1157532 | F54: =F52+F53 -> 2269671 | G54: =G52+G53 -> 1988631 | H54: =H52+H53 -> 603929 | I54: =I52+I53 -> 337078 | J54: =J52+J53 -> 712788
A55: = | B55: NCF | C55: =C49 -> 242430 | D55: =D49 -> 891542 | E55: =E49 -> 1157532 | F55: =F49 -> 2269671 | G55: =G49 -> 1988631 | H55: =H49 -> 603929 | I55: =I49 -> 337078 | J55: =J49 -> 712788
B56: Sbilancio check NCF | C56: =C54-C55 -> 0 | D56: =D54-D55 -> 0 | E56: =E54-E55 -> 0 | F56: =F54-F55 -> 0 | G56: =G54-G55 -> -1.8626451e-09 | H56: =H54-H55 -> -4.6566129e-10 | I56: =I54-I55 -> 0 | J56: =J54-J55 -> 0
B57: Check FCFF
A58: + | B58: EBITDA al netto delle imposte check | C58: =C8 -> 2404683.1 | D58: =D8 -> 2014478.9 | E58: =E8 -> 1799488 | F58: =F8 -> 1680372.5 | G58: =G8 -> 1287696.1 | H58: =H8 -> 1053339.7 | I58: =I8 -> 987252.04 | J58: =J8 -> 714856.17
A59: - | B59: -Ammortamenti check | C59: =-C6 -> -916802 | D59: =-D6 -> -899828 | E59: =-E6 -> -856051 | F59: =-F6 -> -470290 | G59: =-G6 -> -171279 | H59: =-H6 -> -180598 | I59: =-I6 -> -184962 | J59: =-J6 -> -215317
A60: - | B60: - Var (AON* + Att acc - Deb contr coll - Ris riv.) check | C60: =-('RC'!C93+'RC'!C27-'RC'!C66-'RC'!C80) -> -14020790 | D60: =-('RC'!D93+'RC'!D27-'RC'!D66-'RC'!D80) -> -15015841 | E60: =-('RC'!E93+'RC'!E27-'RC'!E66-'RC'!E80) -> -14740723 | F60: =-('RC'!F93+'RC'!F27-'RC'!F66-'RC'!F80) -> -12680324 | G60: =-('RC'!G93+'RC'!G27-'RC'!G66-'RC'!G80) -> -10445663 | H60: =-('RC'!H93+'RC'!H27-'RC'!H66-'RC'!H80) -> -5759820 | I60: =-('RC'!I93+'RC'!I27-'RC'!I66-'RC'!I80) -> -4029785 | J60: =-('RC'!J93+'RC'!J27-'RC'!J66-'RC'!J80) -> -3256444
B61: = Risultato | C61: =C58+C59+C60 -> -12532909 | D61: =D58+D59+D60 -> -13901190 | E61: =E58+E59+E60 -> -13797286 | F61: =F58+F59+F60 -> -11470241 | G61: =G58+G59+G60 -> -9329245.9 | H61: =H58+H59+H60 -> -4887078.3 | I61: =I58+I59+I60 -> -3227495 | J61: =J58+J59+J60 -> -2756904.8
A62: = | B62: = FCFF ceck | C62: =C31 -> -12532909 | D62: =D31 -> -13901190 | E62: =E31 -> -13797286 | F62: =F31 -> -11470241 | G62: =G31 -> -9329245.9 | H62: =H31 -> -4887078.3 | I62: =I31 -> -3227495 | J62: =J31 -> -2756904.8
B63: Sbilancio check FCFF | C63: =C61-C62 -> 0 | D63: =D61-D62 -> 0 | E63: =E61-E62 -> 0 | F63: =F61-F62 -> 0 | G63: =G61-G62 -> 0 | H63: =H61-H62 -> 0 | I63: =I61-I62 -> 0 | J63: =J61-J62 -> 0
B64: Check FCFE
A65: + | B65: Reddito netto check | C65: ='RC'!C150 -> 899733 | D65: ='RC'!D150 -> 566667 | E65: ='RC'!E150 -> 678581 | F65: ='RC'!F150 -> 961303 | G65: ='RC'!G150 -> 921282 | H65: ='RC'!H150 -> 751636 | I65: ='RC'!I150 -> 670425 | J65: ='RC'!J150 -> 364746
A66: - | B66: - Var (AON* + Att acc - Deb contr coll - Ris riv.) check 2 | C66: =-('RC'!C93+'RC'!C27-'RC'!C66-'RC'!C80) -> -14020790 | D66: =-('RC'!D93+'RC'!D27-'RC'!D66-'RC'!D80) -> -15015841 | E66: =-('RC'!E93+'RC'!E27-'RC'!E66-'RC'!E80) -> -14740723 | F66: =-('RC'!F93+'RC'!F27-'RC'!F66-'RC'!F80) -> -12680324 | G66: =-('RC'!G93+'RC'!G27-'RC'!G66-'RC'!G80) -> -10445663 | H66: =-('RC'!H93+'RC'!H27-'RC'!H66-'RC'!H80) -> -5759820 | I66: =-('RC'!I93+'RC'!I27-'RC'!I66-'RC'!I80) -> -4029785 | J66: =-('RC'!J93+'RC'!J27-'RC'!J66-'RC'!J80) -> -3256444
A67: + | B67: + Var (Debito strutt + deriv pass - ris strat liq - deriv att ) check | C67: ='RC'!C69+'RC'!C70-'RC'!C30+'RC'!C72-'RC'!C32 -> 8505933 | D67: ='RC'!D69+'RC'!D70-'RC'!D30+'RC'!D72-'RC'!D32 -> 10679831 | E67: ='RC'!E69+'RC'!E70-'RC'!E30+'RC'!E72-'RC'!E32 -> 11237368 | F67: ='RC'!F69+'RC'!F70-'RC'!F30+'RC'!F72-'RC'!F32 -> 10867692 | G67: ='RC'!G69+'RC'!G70-'RC'!G30+'RC'!G72-'RC'!G32 -> 9228293 | H67: ='RC'!H69+'RC'!H70-'RC'!H30+'RC'!H72-'RC'!H32 -> 3979031 | I67: ='RC'!I69+'RC'!I70-'RC'!I30+'RC'!I72-'RC'!I32 -> 2633782 | J67: ='RC'!J69+'RC'!J70-'RC'!J30+'RC'!J72-'RC'!J32 -> 2906574
B68: = Risultato | C68: =C65+C66+C67 -> -4615124 | D68: =D65+D66+D67 -> -3769343 | E68: =E65+E66+E67 -> -2824774 | F68: =F65+F66+F67 -> -851329 | G68: =G65+G66+G67 -> -296088 | H68: =H65+H66+H67 -> -1029153 | I68: =I65+I66+I67 -> -725578 | J68: =J65+J66+J67 -> 14876
A69: = | B69: = FCFE check | C69: =C41 -> -4615124 | D69: =D41 -> -3769343 | E69: =E41 -> -2824774 | F69: =F41 -> -851329 | G69: =G41 -> -296088 | H69: =H41 -> -1029153 | I69: =I41 -> -725578 | J69: =J41 -> 14876
B70: Sbilancio check FCFE | C70: =C68-C69 -> 0 | D70: =D68-D69 -> 0 | E70: =E68-E69 -> 0 | F70: =F68-F69 -> 0 | G70: =G68-G69 -> -1.8626451e-09 | H70: =H68-H69 -> -4.6566129e-10 | I70: =I68-I69 -> 0 | J70: =J68-J69 -> 0

Sheet ind
A1: INDICATORI FINANZIARI | B1: =RF!C1 -> 31/12/2024 | C1: =RF!D1 -> 31/12/2023 | D1: =RF!E1 -> 31/12/2022 | E1: =RF!F1 -> 31/12/2021 | F1: =RF!G1 -> 31/12/2020 | G1: =RF!H1 -> 31/12/2019 | H1: =RF!I1 -> 31/12/2018 | I1: =RF!J1 -> 31/12/2017
A2: valori patrimoniali medie t-1 per attenuare variazioni significativi
A3: RLA (redd. gest OFA) | B3: ='RC'!C131+'RC'!C140+'RC'!C144 -> 1087201 | C3: ='RC'!D131+'RC'!D140+'RC'!D144 -> 591071 | D3: ='RC'!E131+'RC'!E140+'RC'!E144 -> 710509 | E3: ='RC'!F131+'RC'!F140+'RC'!F144 -> 1204240 | F3: ='RC'!G131+'RC'!G140+'RC'!G144 -> 1192771 | G3: ='RC'!H131+'RC'!H140+'RC'!H144 -> 970828 | H3: ='RC'!I131+'RC'!I140+'RC'!I144 -> 951134 | I3: ='RC'!J131+'RC'!J140+'RC'!J144 -> 533439
A4: Reddito operativo | B4: ='RC'!C131 -> 1588849 | C4: ='RC'!D131 -> 1117327 | D4: ='RC'!E131 -> 963975 | E4: ='RC'!F131 -> 1411257 | F4: ='RC'!G131 -> 1351726 | G4: ='RC'!H131 -> 1069627 | H4: ='RC'!I131 -> 1052950 | I4: ='RC'!J131 -> 635847
A5: EBITDA(MOL) | B5: ='RC'!C123 -> 2481804 | C5: ='RC'!D123 -> 1835259 | D5: ='RC'!E123 -> 1706003 | E5: ='RC'!F123 -> 1926582 | F5: ='RC'!G123 -> 1540277 | G5: ='RC'!H123 -> 1357618 | H5: ='RC'!I123 -> 1405132 | I5: ='RC'!J123 -> 1124651
A6: Reddito netto | B6: ='RC'!C150 -> 899733 | C6: ='RC'!D150 -> 566667 | D6: ='RC'!E150 -> 678581 | E6: ='RC'!F150 -> 961303 | F6: ='RC'!G150 -> 921282 | G6: ='RC'!H150 -> 751636 | H6: ='RC'!I150 -> 670425 | I6: ='RC'!J150 -> 364746
A7: Ricavi | B7: ='RC'!C111 -> 21650995 | C7: ='RC'!D111 -> 21142391 | D7: ='RC'!E111 -> 17821289 | E7: ='RC'!F111 -> 15638358 | F7: ='RC'!G111 -> 14336879 | G7: ='RC'!H111 -> 13550152 | H7: ='RC'!I111 -> 11519434 | I7: ='RC'!J111 -> 9917341
A8: Ricavi t-1 | B8: ='RC'!D111 -> 21142391 | C8: ='RC'!E111 -> 17821289 | D8: ='RC'!F111 -> 15638358 | E8: ='RC'!G111 -> 14336879 | F8: ='RC'!H111 -> 13550152 | G8: ='RC'!I111 -> 11519434 | H8: ='RC'!J111 -> 9917341 | I8: ='RC'!#REF! -> #ERROR!
A9: Ricavi con IVA gg | B9: =B7*1.22/365 -> 72367.709 | C9: =C7*1.22/365 -> 70667.718 | D9: =D7*1.22/365 -> 59567.048 | E9: =E7*1.22/365 -> 52270.676 | F9: =F7*1.22/365 -> 47920.527 | G9: =G7*1.22/365 -> 45290.919 | H9: =H7*1.22/365 -> 38503.314 | I9: =I7*1.22/365 -> 33148.373
A10: Acquisti | B10: ='RC'!C116 -> -17239201 | C10: ='RC'!D116 -> -17541147 | D10: ='RC'!E116 -> -16838729 | E10: ='RC'!F116 -> -12600246 | F10: ='RC'!G116 -> -11051119 | G10: ='RC'!H116 -> -11504899 | H10: ='RC'!I116 -> -9369872 | I10: ='RC'!J116 -> -7915457
A11: Acquisti con IVA gg | B11: ='RC'!C116*1.22/365 -> -57621.439 | C11: ='RC'!D116*1.22/365 -> -58630.683 | D11: ='RC'!E116*1.22/365 -> -56282.875 | E11: ='RC'!F116*1.22/365 -> -42115.891 | F11: ='RC'!G116*1.22/365 -> -36937.987 | G11: ='RC'!H116*1.22/365 -> -38454.731 | H11: ='RC'!I116*1.22/365 -> -31318.476 | I11: ='RC'!J116*1.22/365 -> -26457.144
A12: Costo del venduto gg medio | B12: =AVERAGE('RC'!C120:D120)/365 -> -48523.011 | C12: =AVERAGE('RC'!D120:E120)/365 -> -44197.125 | D12: =AVERAGE('RC'!E120:F120)/365 -> -36637.518 | E12: =AVERAGE('RC'!F120:G120)/365 -> -32517.418 | F12: =AVERAGE('RC'!G120:H120)/365 -> -30714.495 | G12: =AVERAGE('RC'!H120:I120)/365 -> -27307.786 | H12: =AVERAGE('RC'!I120:J120)/365 -> -23215.595 | I12: =AVERAGE('RC'!J120)/365 -> -21723.611
A13: Costo del personale gg medio | B13: =AVERAGE('RC'!C122:D122)/365 -> -4184.2808 | C13: =AVERAGE('RC'!D122:E122)/365 -> -4326.7356 | D13: =AVERAGE('RC'!E122:F122)/365 -> -4221.4712 | E13: =AVERAGE('RC'!F122:G122)/365 -> -3795.4288 | F13: =AVERAGE('RC'!G122:H122)/365 -> -3517.1986 | G13: =AVERAGE('RC'!H122:I122)/365 -> -3249.5233 | H13: =AVERAGE('RC'!I122:J122)/365 -> -2684.3945 | I13: =AVERAGE('RC'!J122)/365 -> -2365.9507
A14: AON* medio | B14: =AVERAGE('RC'!C93,'RC'!D93) -> 14459614 | C14: =AVERAGE('RC'!D93,'RC'!E93) -> 14819580 | D14: =AVERAGE('RC'!E93,'RC'!F93) -> 13651822 | E14: =AVERAGE('RC'!F93,'RC'!G93) -> 11530386 | F14: =AVERAGE('RC'!G93,'RC'!H93) -> 8096229.5 | G14: =AVERAGE('RC'!H93,'RC'!I93) -> 4888290.5 | H14: =AVERAGE('RC'!I93,'RC'!J93) -> 3636602.5 | I14: =AVERAGE('RC'!I93,'RC'!#REF!) -> #ERROR!
A15: AON* init | B15: ='RC'!D93 -> 14957139 | C15: ='RC'!E93 -> 14682021 | D15: ='RC'!F93 -> 12621622 | E15: ='RC'!G93 -> 10439151 | F15: ='RC'!H93 -> 5753308 | G15: ='RC'!I93 -> 4023273 | H15: ='RC'!J93 -> 3249932 | I15: ='RC'!#REF! -> #ERROR!
A16: AON* fin | B16: ='RC'!C93 -> 13962088 | C16: ='RC'!D93 -> 14957139 | D16: ='RC'!E93 -> 14682021 | E16: ='RC'!F93 -> 12621622 | F16: ='RC'!G93 -> 10439151 | G16: ='RC'!H93 -> 5753308 | H16: ='RC'!I93 -> 4023273 | I16: ='RC'!J93 -> 3249932
A17: Reddito att.acc (prov-oneri acc) | B17: ='RC'!C144 -> 0 | C17: ='RC'!D144 -> 0 | D17: ='RC'!E144 -> 0 | E17: ='RC'!F144 -> 0 | F17: ='RC'!G144 -> 0 | G17: ='RC'!H144 -> 0 | H17: ='RC'!I144 -> 0 | I17: ='RC'!J144 -> 0
A18: AACCN media(ris gest acc) | B18: =AVERAGE('RC'!C94,'RC'!D94) -> 58702 | C18: =AVERAGE('RC'!D94,'RC'!E94) -> 58702 | D18: =AVERAGE('RC'!E94,'RC'!F94) -> 58702 | E18: =AVERAGE('RC'!F94,'RC'!G94) -> 32607 | F18: =AVERAGE('RC'!G94,'RC'!H94) -> 6512 | G18: =AVERAGE('RC'!H94,'RC'!I94) -> 6512 | H18: =AVERAGE('RC'!I94,'RC'!J94) -> 6512 | I18: =AVERAGE('RC'!I94,'RC'!#REF!) -> #ERROR!
A19: AACC medie(solo attività) | B19: =AVERAGE('RC'!C27,'RC'!D27) -> 58702 | C19: =AVERAGE('RC'!D27,'RC'!E27) -> 58702 | D19: =AVERAGE('RC'!E27,'RC'!F27) -> 58702 | E19: =AVERAGE('RC'!F27,'RC'!G27) -> 32607 | F19: =AVERAGE('RC'!G27,'RC'!H27) -> 6512 | G19: =AVERAGE('RC'!H27,'RC'!I27) -> 6512 | H19: =AVERAGE('RC'!I27,'RC'!J27) -> 6512 | I19: =AVERAGE('RC'!I27,'RC'!#REF!) -> #ERROR!
A20: AACC finali | B20: ='RC'!C27 -> 58702 | C20: ='RC'!D27 -> 58702 | D20: ='RC'!E27 -> 58702 | E20: ='RC'!F27 -> 58702 | F20: ='RC'!G27 -> 6512 | G20: ='RC'!H27 -> 6512 | H20: ='RC'!I27 -> 6512 | I20: ='RC'!J27 -> 6512
A21: PACC medie (solo passivo) | B21: =AVERAGE('RC'!C66,'RC'!D66) -> 0 | C21: =AVERAGE('RC'!D66,'RC'!E66) -> 0 | D21: =AVERAGE('RC'!E66,'RC'!F66) -> 0 | E21: =AVERAGE('RC'!F66,'RC'!G66) -> 0 | F21: =AVERAGE('RC'!G66,'RC'!H66) -> 0 | G21: =AVERAGE('RC'!H66,'RC'!I66) -> 0 | H21: =AVERAGE('RC'!I66,'RC'!J66) -> 0 | I21: =AVERAGE('RC'!I66,'RC'!#REF!) -> #ERROR!
A22: PACC finali (solo passivo) | B22: ='RC'!C66 -> 0 | C22: ='RC'!D66 -> 0 | D22: ='RC'!E66 -> 0 | E22: ='RC'!F66 -> 0 | F22: ='RC'!G66 -> 0 | G22: ='RC'!H66 -> 0 | H22: ='RC'!I66 -> 0 | I22: ='RC'!J66 -> 0
A23: ris gest str | B23: ='RC'!C145 -> 0 | C23: ='RC'!D145 -> 0 | D23: ='RC'!E145 -> 0 | E23: ='RC'!F145 -> 0 | F23: ='RC'!G145 -> 0 | G23: ='RC'!H145 -> 0 | H23: ='RC'!I145 -> 0 | I23: ='RC'!J145 -> 0
A24: PFN (ris gest fin) | B24: =B30-B31 -> 9025896 | C24: =C30-C31 -> 9934062.5 | D24: =D30-D31 -> 9338928.5 | E24: =E30-E31 -> 7918841.5 | F24: =F30-F31 -> 5307382 | G24: =G30-G31 -> 2835903 | H24: =H30-H31 -> 2245245 | I24: =I30-I31 -> #ERROR!
A25: DEBn | B25: =IF(B24>0, B24, 0) -> 9025896 | C25: =IF(C24>0, C24, 0) -> 9934062.5 | D25: =IF(D24>0, D24, 0) -> 9338928.5 | E25: =IF(E24>0, E24, 0) -> 7918841.5 | F25: =IF(F24>0, F24, 0) -> 5307382 | G25: =IF(G24>0, G24, 0) -> 2835903 | H25: =IF(H24>0, H24, 0) -> 2245245 | I25: =IF(I24>0, I24, 0) -> #ERROR!
A26: LIQn | B26: =IF(B24<0, -B24, 0) -> 0 | C26: =IF(C24<0, C24, 0) -> 0 | D26: =IF(D24<0, D24, 0) -> 0 | E26: =IF(E24<0, E24, 0) -> 0 | F26: =IF(F24<0, F24, 0) -> 0 | G26: =IF(G24<0, G24, 0) -> 0 | H26: =IF(H24<0, H24, 0) -> 0 | I26: =IF(I24<0, I24, 0) -> #ERROR!
A27: oneri finanziari | B27: ='RC'!C138 -> -503404 | C27: ='RC'!D138 -> -528343 | D27: ='RC'!E138 -> -253674 | E27: ='RC'!F138 -> -207408 | F27: ='RC'!G138 -> -159160 | G27: ='RC'!H138 -> -102930 | H27: ='RC'!I138 -> -102001 | I27: ='RC'!J138 -> -102507
A28: interessi attivi | B28: ='RC'!C137 -> 1756 | C28: ='RC'!D137 -> 2087 | D28: ='RC'!E137 -> 208 | E28: ='RC'!F137 -> 391 | F28: ='RC'!G137 -> 205 | G28: ='RC'!H137 -> 4131 | H28: ='RC'!I137 -> 185 | I28: ='RC'!J137 -> 99
A29: imposta | B29: ='RC'!C149 -> -187468 | C29: ='RC'!D149 -> -24404 | D29: ='RC'!E149 -> -31928 | E29: ='RC'!F149 -> -242937 | F29: ='RC'!G149 -> -271489 | G29: ='RC'!H149 -> -219192 | H29: ='RC'!I149 -> -280709 | I29: ='RC'!J149 -> -168693
A30: Debito lordo medio(pass. gest. fin) | B30: =AVERAGE('RC'!C73,'RC'!D73) -> 9592882 | C30: =AVERAGE('RC'!D73,'RC'!E73) -> 10958600 | D30: =AVERAGE('RC'!E73,'RC'!F73) -> 11052530 | E30: =AVERAGE('RC'!F73,'RC'!G73) -> 10047992 | F30: =AVERAGE('RC'!G73,'RC'!H73) -> 6603662 | G30: =AVERAGE('RC'!H73,'RC'!I73) -> 3306406.5 | H30: =AVERAGE('RC'!I73,'RC'!J73) -> 2770178 | I30: =AVERAGE('RC'!I73,'RC'!#REF!) -> #ERROR!
A31: Liq. lorda media(att. gest fin) | B31: =AVERAGE('RC'!C33,'RC'!D33) -> 566986 | C31: =AVERAGE('RC'!D33,'RC'!E33) -> 1024537 | D31: =AVERAGE('RC'!E33,'RC'!F33) -> 1713601.5 | E31: =AVERAGE('RC'!F33,'RC'!G33) -> 2129151 | F31: =AVERAGE('RC'!G33,'RC'!H33) -> 1296280 | G31: =AVERAGE('RC'!H33,'RC'!I33) -> 470503.5 | H31: =AVERAGE('RC'!I33,'RC'!J33) -> 524933 | I31: =AVERAGE('RC'!I33,'RC'!#REF!) -> #ERROR!
A32: Crediti commerciali medi | B32: =AVERAGE('RC'!C5:D5) -> 4076587.5 | C32: =AVERAGE('RC'!D5:E5) -> 3431489.5 | D32: =AVERAGE('RC'!E5:F5) -> 3073409.5 | E32: =AVERAGE('RC'!F5:G5) -> 2983914 | F32: =AVERAGE('RC'!G5:H5) -> 2715056.5 | G32: =AVERAGE('RC'!H5:I5) -> 2498211 | H32: =AVERAGE('RC'!I5:J5) -> 2367411.5 | I32: =AVERAGE('RC'!J5) -> 2381302
A33: Debiti commerciali medi | B33: =AVERAGE('RC'!C48,'RC'!D48) -> 2308640.5 | C33: =AVERAGE('RC'!D48,'RC'!E48) -> 2430353.5 | D33: =AVERAGE('RC'!E48,'RC'!F48) -> 2329921 | E33: =AVERAGE('RC'!F48,'RC'!G48) -> 1763975.5 | F33: =AVERAGE('RC'!G48,'RC'!H48) -> 1734486 | G33: =AVERAGE('RC'!H48,'RC'!I48) -> 1639495 | H33: =AVERAGE('RC'!I48,'RC'!J48) -> 1229982 | I33: =AVERAGE('RC'!I48,'RC'!#REF!) -> #ERROR!
A34: Rimanenze magazzino medie | B34: =AVERAGE('RC'!C6,'RC'!D6) -> 4824580 | C34: =AVERAGE('RC'!D6,'RC'!E6) -> 5145305 | D34: =AVERAGE('RC'!E6,'RC'!F6) -> 4087317.5 | E34: =AVERAGE('RC'!F6,'RC'!G6) -> 2740524.5 | F34: =AVERAGE('RC'!G6,'RC'!H6) -> 2783699.5 | G34: =AVERAGE('RC'!H6,'RC'!I6) -> 2716481 | H34: =AVERAGE('RC'!I6,'RC'!J6) -> 2246438 | I34: =AVERAGE('RC'!I6,'RC'!#REF!) -> #ERROR!
A35: Rimanenze magazzino finali | B35: ='RC'!C6 -> 4608814 | C35: ='RC'!D6 -> 5040346 | D35: ='RC'!E6 -> 5250264 | E35: ='RC'!F6 -> 2924371 | F35: ='RC'!G6 -> 2556678 | G35: ='RC'!H6 -> 3010721 | H35: ='RC'!I6 -> 2422241 | I35: ='RC'!J6 -> 2070635
A36: Attività a BT | B36: =AVERAGE('RC'!C8:D8)+AVERAGE('RC'!C19:D19)+AVERAGE('RC'!C30:D30) -> 10092731 | C36: =AVERAGE('RC'!D8:E8)+AVERAGE('RC'!D19:E19)+AVERAGE('RC'!D30:E30) -> 10215282 | D36: =AVERAGE('RC'!E8:F8)+AVERAGE('RC'!E19:F19)+AVERAGE('RC'!E30:F30) -> 8159909.5 | E36: =AVERAGE('RC'!F8:G8)+AVERAGE('RC'!F19:G19)+AVERAGE('RC'!F30:G30) -> 6051218.5 | F36: =AVERAGE('RC'!G8:H8)+AVERAGE('RC'!G19:H19)+AVERAGE('RC'!G30:H30) -> 5912189.5 | G36: =AVERAGE('RC'!H8:I8)+AVERAGE('RC'!H19:I19)+AVERAGE('RC'!H30:I30) -> 5504005 | H36: =AVERAGE('RC'!I8:J8)+AVERAGE('RC'!I19:J19)+AVERAGE('RC'!I30:J30) -> 4723640 | I36: =AVERAGE('RC'!J8)+AVERAGE('RC'!J19)+AVERAGE('RC'!J30) -> 4530450
A37: Attività a BT finali | B37: ='RC'!C8+'RC'!C19+'RC'!C30 -> 9705479 | C37: ='RC'!D8+'RC'!D19+'RC'!D30 -> 10479983 | D37: ='RC'!E8+'RC'!E19+'RC'!E30 -> 9950581 | E37: ='RC'!F8+'RC'!F19+'RC'!F30 -> 6369238 | F37: ='RC'!G8+'RC'!G19+'RC'!G30 -> 5733199 | G37: ='RC'!H8+'RC'!H19+'RC'!H30 -> 6091180 | H37: ='RC'!I8+'RC'!I19+'RC'!I30 -> 4916830 | I37: ='RC'!J8+'RC'!J19+'RC'!J30 -> 4530450
A38: Passività a BT medie | B38: =AVERAGE('RC'!C51:D51)+AVERAGE('RC'!C59:D59)+AVERAGE('RC'!C70:D70) -> 8093679.5 | C38: =AVERAGE('RC'!D51:E51)+AVERAGE('RC'!D59:E59)+AVERAGE('RC'!D70:E70) -> 8805614 | D38: =AVERAGE('RC'!E51:F51)+AVERAGE('RC'!E59:F59)+AVERAGE('RC'!E70:F70) -> 7854147.5 | E38: =AVERAGE('RC'!F51:G51)+AVERAGE('RC'!F59:G59)+AVERAGE('RC'!F70:G70) -> 5831649 | F38: =AVERAGE('RC'!G51:H51)+AVERAGE('RC'!G59:H59)+AVERAGE('RC'!G70:H70) -> 5621201 | G38: =AVERAGE('RC'!H51:I51)+AVERAGE('RC'!H59:I59)+AVERAGE('RC'!H70:I70) -> 4908556 | H38: =AVERAGE('RC'!I51:J51)+AVERAGE('RC'!I59:J59)+AVERAGE('RC'!I70:J70) -> 3803690.5 | I38: =AVERAGE('RC'!J51)+AVERAGE('RC'!J59)+AVERAGE('RC'!J70) -> 3922106
A39: Passività a BT finali | B39: ='RC'!C51+'RC'!C59+'RC'!C70 -> 7731693 | C39: ='RC'!D51+'RC'!D59+'RC'!D70 -> 8455666 | D39: ='RC'!E51+'RC'!E59+'RC'!E70 -> 9155562 | E39: ='RC'!F51+'RC'!F59+'RC'!F70 -> 6552733 | F39: ='RC'!G51+'RC'!G59+'RC'!G70 -> 5110565 | G39: ='RC'!H51+'RC'!H59+'RC'!H70 -> 6131837 | H39: ='RC'!I51+'RC'!I59+'RC'!I70 -> 3685275 | I39: ='RC'!J51+'RC'!J59+'RC'!J70 -> 3922106
A40: Passività operative consolidate medie | B40: =AVERAGE('RC'!C52,'RC'!D52) -> 0 | C40: =AVERAGE('RC'!D52,'RC'!E52) -> 0 | D40: =AVERAGE('RC'!E52,'RC'!F52) -> 0 | E40: =AVERAGE('RC'!F52,'RC'!G52) -> 0 | F40: =AVERAGE('RC'!G52,'RC'!H52) -> 0 | G40: =AVERAGE('RC'!H52,'RC'!I52) -> 0 | H40: =AVERAGE('RC'!I52,'RC'!J52) -> 0 | I40: =AVERAGE('RC'!I52,'RC'!#REF!) -> #ERROR!
A41: Passività operative consolidate finali | B41: ='RC'!C52 -> 0 | C41: ='RC'!D52 -> 0 | D41: ='RC'!E52 -> 0 | E41: ='RC'!F52 -> 0 | F41: ='RC'!G52 -> 0 | G41: ='RC'!H52 -> 0 | H41: ='RC'!I52 -> 0 | I41: ='RC'!J52 -> 0
A42: debiti strutturali m/l medi | B42: =AVERAGE('RC'!C69,'RC'!D69) -> 5901038.5 | C42: =AVERAGE('RC'!D69,'RC'!E69) -> 6704693 | D42: =AVERAGE('RC'!E69,'RC'!F69) -> 7044854 | E42: =AVERAGE('RC'!F69,'RC'!G69) -> 6838124 | F42: =AVERAGE('RC'!G69,'RC'!H69) -> 3446170 | G42: =AVERAGE('RC'!H69,'RC'!I69) -> 698341 | H42: =AVERAGE('RC'!I69,'RC'!J69) -> 880329.5 | I42: =AVERAGE('RC'!I69,'RC'!#REF!) -> #ERROR!
A43: debiti strutturali m/l finali | B43: ='RC'!C69 -> 5110204 | C43: ='RC'!D69 -> 6691873 | D43: ='RC'!E69 -> 6717513 | E43: ='RC'!F69 -> 7372195 | F43: ='RC'!G69 -> 6304053 | G43: ='RC'!H69 -> 588287 | H43: ='RC'!I69 -> 808395 | I43: ='RC'!J69 -> 952264
A44: immobilizzazioni operative | B44: =(('RC'!C12+'RC'!C15)+'RC'!D12+'RC'!D15)/2 -> 8954199 | C44: =(('RC'!D12+'RC'!D15)+'RC'!E12+'RC'!E15)/2 -> 9340197.5 | D44: =(('RC'!E12+'RC'!E15)+'RC'!F12+'RC'!F15)/2 -> 9531622.5 | E44: =(('RC'!F12+'RC'!F15)+'RC'!G12+'RC'!G15)/2 -> 8286834.5 | F44: =(('RC'!G12+'RC'!G15)+'RC'!H12+'RC'!H15)/2 -> 4838223 | G44: =(('RC'!H12+'RC'!H15)+'RC'!I12+'RC'!I15)/2 -> 1902194 | H44: =(('RC'!I12+'RC'!I15)+'RC'!J12+'RC'!J15)/2 -> 1048299 | I44: =(('RC'!I12+'RC'!I15)+'RC'!#REF!+'RC'!#REF!)/2 -> #ERROR!
A45: immobilizzazioni operative finali | B45: ='RC'!C12 -> 8784248 | C45: ='RC'!D12 -> 9124150 | D45: ='RC'!E12 -> 9556245 | E45: ='RC'!F12 -> 9507000 | F45: ='RC'!G12 -> 7058477 | G45: ='RC'!H12 -> 2601585 | H45: ='RC'!I12 -> 1186419 | I45: ='RC'!J12 -> 893795
A46: CP capitale proprio medio | B46: =AVERAGE('RC'!C84,'RC'!D84) -> 5492419.5 | C46: =AVERAGE('RC'!D84,'RC'!E84) -> 4944219.5 | D46: =AVERAGE('RC'!E84,'RC'!F84) -> 4371595 | E46: =AVERAGE('RC'!F84,'RC'!G84) -> 3644152 | F46: =AVERAGE('RC'!G84,'RC'!H84) -> 2795359.5 | G46: =AVERAGE('RC'!H84,'RC'!I84) -> 2058899.5 | H46: =AVERAGE('RC'!I84,'RC'!J84) -> 1397869.5 | I46: =AVERAGE('RC'!I84,'RC'!#REF!) -> #ERROR!
A47: CP init | B47: ='RC'!D84 -> 5227552 | C47: ='RC'!E84 -> 4660887 | D47: ='RC'!F84 -> 4082303 | E47: ='RC'!G84 -> 3206001 | F47: ='RC'!H84 -> 2384718 | G47: ='RC'!I84 -> 1733081 | H47: ='RC'!J84 -> 1062658 | I47: ='RC'!#REF! -> #ERROR!
A48: CP fin | B48: ='RC'!C84 -> 5757287 | C48: ='RC'!D84 -> 5227552 | D48: ='RC'!E84 -> 4660887 | E48: ='RC'!F84 -> 4082303 | F48: ='RC'!G84 -> 3206001 | G48: ='RC'!H84 -> 2384718 | H48: ='RC'!I84 -> 1733081 | I48: ='RC'!J84 -> 1062658
A49: DIV t | B49: ='RC'!D82+'RC'!D79-'RC'!C79 -> 369998 | C49: ='RC'!E82+'RC'!E79-'RC'!D79 -> 2 | D49: ='RC'!F82+'RC'!F79-'RC'!E79 -> 99997 | E49: ='RC'!G82+'RC'!G79-'RC'!F79 -> 85001 | F49: ='RC'!H82+'RC'!H79-'RC'!G79 -> 99999 | G49: ='RC'!I82+'RC'!I79-'RC'!H79 -> 99999 | H49: ='RC'!J82+'RC'!J79-'RC'!I79 -> 2 | I49: ='RC'!#REF!+'RC'!#REF!-'RC'!I79 -> #ERROR!
A50: Aumento finanziamenti netti da soci e controllanti t e t-1 | B50: ='RC'!C76-'RC'!D76 -> 0 | C50: ='RC'!D76-'RC'!E76 -> 0 | D50: ='RC'!E76-'RC'!F76 -> 0 | E50: ='RC'!F76-'RC'!G76 -> 0 | F50: ='RC'!G76-'RC'!H76 -> 0 | G50: ='RC'!H76-'RC'!I76 -> 0 | H50: ='RC'!I76-'RC'!J76 -> 0 | I50: ='RC'!I76-'RC'!#REF! -> #ERROR!
A51: Aumento accantonamenti e perdite precedenti (se neg aumento utile) | B51: =RF!C43-RF!D43 -> 196669 | C51: =RF!D43-RF!E43 -> 678579 | D51: =RF!E43-RF!F43 -> 861306 | E51: =RF!F43-RF!G43 -> 836281 | F51: =RF!G43-RF!H43 -> 651637 | G51: =RF!H43-RF!I43 -> 570426 | H51: =RF!I43-RF!J43 -> 364744 | I51: =RF!J43-RF!#REF! -> #ERROR!
A52: var reddito di esercizio | B52: ='RC'!C82-'RC'!D82 -> 333066 | C52: ='RC'!D82-'RC'!E82 -> -111914 | D52: ='RC'!E82-'RC'!F82 -> -282722 | E52: ='RC'!F82-'RC'!G82 -> 40021 | F52: ='RC'!G82-'RC'!H82 -> 169646 | G52: ='RC'!H82-'RC'!I82 -> 81211 | H52: ='RC'!I82-'RC'!J82 -> 305679 | I52: ='RC'!I82-'RC'!#REF! -> #ERROR!
A53: var CPn | B53: ='RC'!C77-'RC'!D77 -> 529735 | C53: ='RC'!D77-'RC'!E77 -> 566665 | D53: ='RC'!E77-'RC'!F77 -> 578584 | E53: ='RC'!F77-'RC'!G77 -> 876302 | F53: ='RC'!G77-'RC'!H77 -> 821283 | G53: ='RC'!H77-'RC'!I77 -> 651637 | H53: ='RC'!I77-'RC'!J77 -> 670423 | I53: ='RC'!I77-'RC'!#REF! -> #ERROR!
A56: INDICATORI FINANZIARI | B56: =B1 -> 31/12/2024 | C56: =C1 -> 31/12/2023 | D56: =D1 -> 31/12/2022 | E56: =E1 -> 31/12/2021 | F56: =F1 -> 31/12/2020 | G56: =G1 -> 31/12/2019 | H56: =H1 -> 31/12/2018 | I56: =I1 -> 31/12/2017
A57: Quozienti di redditività
A58: Reddito operativo | B58: =B4 -> 1588849 | C58: =C4 -> 1117327 | D58: =D4 -> 963975 | E58: =E4 -> 1411257 | F58: =F4 -> 1351726 | G58: =G4 -> 1069627 | H58: =H4 -> 1052950 | I58: =I4 -> 635847
A59: /Ricavi | B59: =B7 -> 21650995 | C59: =C7 -> 21142391 | D59: =D7 -> 17821289 | E59: =E7 -> 15638358 | F59: =F7 -> 14336879 | G59: =G7 -> 13550152 | H59: =H7 -> 11519434 | I59: =I7 -> 9917341
A60: ROS | B60: =B58/B59 -> 0.073384572 | C60: =C58/C59 -> 0.052847712 | D60: =D58/D59 -> 0.054091205 | E60: =E58/E59 -> 0.090243298 | F60: =F58/F59 -> 0.094283142 | G60: =G58/G59 -> 0.078938376 | H60: =H58/H59 -> 0.091406401 | I60: =I58/I59 -> 0.064114665
A62: Reddito operativo | B62: =B4 -> 1588849 | C62: =C4 -> 1117327 | D62: =D4 -> 963975 | E62: =E4 -> 1411257 | F62: =F4 -> 1351726 | G62: =G4 -> 1069627 | H62: =H4 -> 1052950 | I62: =I4 -> 635847
A63: /AON* | B63: =B14 -> 14459614 | C63: =C14 -> 14819580 | D63: =D14 -> 13651822 | E63: =E14 -> 11530386 | F63: =F14 -> 8096229.5 | G63: =G14 -> 4888290.5 | H63: =H14 -> 3636602.5 | I63: =I14 -> #ERROR!
A64: ROI | B64: =B62/B63 -> 0.10988184 | C64: =C62/C63 -> 0.075395322 | D64: =D62/D63 -> 0.070611457 | E64: =E62/E63 -> 0.1223946 | F64: =F62/F63 -> 0.16695747 | G64: =G62/G63 -> 0.21881412 | H64: =H62/H63 -> 0.28954223 | I64: =I62/I63 -> #ERROR!
A66: Oneri finanziari | B66: =-B27 -> 503404 | C66: =-C27 -> 528343 | D66: =-D27 -> 253674 | E66: =-E27 -> 207408 | F66: =-F27 -> 159160 | G66: =-G27 -> 102930 | H66: =-H27 -> 102001 | I66: =-I27 -> 102507
A67: /Debito lordo | B67: =B30 -> 9592882 | C67: =C30 -> 10958600 | D67: =D30 -> 11052530 | E67: =E30 -> 10047992 | F67: =F30 -> 6603662 | G67: =G30 -> 3306406.5 | H67: =H30 -> 2770178 | I67: =I30 -> #ERROR!
A68: ROD | B68: =B66/B67 -> 0.052476826 | C68: =C66/C67 -> 0.048212639 | D68: =D66/D67 -> 0.022951668 | E68: =E66/E67 -> 0.020641735 | F68: =F66/F67 -> 0.024101779 | G68: =G66/G67 -> 0.031130474 | H68: =H66/H67 -> 0.0368211 | I68: =I66/I67 -> #ERROR!
A70: Interessi attivi | B70: =B28 -> 1756 | C70: =C28 -> 2087 | D70: =D28 -> 208 | E70: =E28 -> 391 | F70: =F28 -> 205 | G70: =G28 -> 4131 | H70: =H28 -> 185 | I70: =I28 -> 99
A71: /Liquidità lorda | B71: =B31 -> 566986 | C71: =C31 -> 1024537 | D71: =D31 -> 1713601.5 | E71: =E31 -> 2129151 | F71: =F31 -> 1296280 | G71: =G31 -> 470503.5 | H71: =H31 -> 524933 | I71: =I31 -> #ERROR!
A72: ROL | B72: =B70/B71 -> 0.0030970782 | C72: =C70/C71 -> 0.0020370177 | D72: =D70/D71 -> 0.00012138178 | E72: =E70/E71 -> 0.00018364127 | F72: =F70/F71 -> 0.00015814485 | G72: =G70/G71 -> 0.0087799559 | H72: =H70/H71 -> 0.00035242593 | I72: =I70/I71 -> #ERROR!
A74: Reddittività att.acc | B74: =B17 -> 0 | C74: =C17 -> 0 | D74: =D17 -> 0 | E74: =E17 -> 0 | F74: =F17 -> 0 | G74: =G17 -> 0 | H74: =H17 -> 0 | I74: =I17 -> 0
A75: /AACCn | B75: =B18 -> 58702 | C75: =C18 -> 58702 | D75: =D18 -> 58702 | E75: =E18 -> 32607 | F75: =F18 -> 6512 | G75: =G18 -> 6512 | H75: =H18 -> 6512 | I75: =I18 -> #ERROR!
A76: ROAACC | B76: =B74/B75 -> 0 | C76: =C74/C75 -> 0 | D76: =D74/D75 -> 0 | E76: =E74/E75 -> 0 | F76: =F74/F75 -> 0 | G76: =G74/G75 -> 0 | H76: =H74/H75 -> 0 | I76: =I74/I75 -> #ERROR!
A78: Reddito netto | B78: =B6 -> 899733 | C78: =C6 -> 566667 | D78: =D6 -> 678581 | E78: =E6 -> 961303 | F78: =F6 -> 921282 | G78: =G6 -> 751636 | H78: =H6 -> 670425 | I78: =I6 -> 364746
A79: /CP | B79: =B46 -> 5492419.5 | C79: =C46 -> 4944219.5 | D79: =D46 -> 4371595 | E79: =E46 -> 3644152 | F79: =F46 -> 2795359.5 | G79: =G46 -> 2058899.5 | H79: =H46 -> 1397869.5 | I79: =I46 -> #ERROR!
A80: ROE netto | B80: =B78/B79 -> 0.1638136 | C80: =C78/C79 -> 0.11461202 | D80: =D78/D79 -> 0.15522504 | E80: =E78/E79 -> 0.26379333 | F80: =F78/F79 -> 0.3295755 | G80: =G78/G79 -> 0.36506687 | H80: =H78/H79 -> 0.47960486 | I80: =I78/I79 -> #ERROR!
A82: RLA | B82: =B3 -> 1087201 | C82: =C3 -> 591071 | D82: =D3 -> 710509 | E82: =E3 -> 1204240 | F82: =F3 -> 1192771 | G82: =G3 -> 970828 | H82: =H3 -> 951134 | I82: =I3 -> 533439
A83: /CP | B83: =B46 -> 5492419.5 | C83: =C46 -> 4944219.5 | D83: =D46 -> 4371595 | E83: =E46 -> 3644152 | F83: =F46 -> 2795359.5 | G83: =G46 -> 2058899.5 | H83: =H46 -> 1397869.5 | I83: =I46 -> #ERROR!
A84: ROE lordo | B84: =B82/B83 -> 0.19794573 | C84: =C82/C83 -> 0.11954789 | D84: =D82/D83 -> 0.16252855 | E84: =E82/E83 -> 0.33045822 | F84: =F82/F83 -> 0.42669682 | G84: =G82/G83 -> 0.47152763 | H84: =H82/H83 -> 0.68041688 | I84: =I82/I83 -> #ERROR!
A86: Prima scomposizione ROE lordo:
A87: ROI | B87: =B64 -> 0.10988184 | C87: =C64 -> 0.075395322 | D87: =D64 -> 0.070611457 | E87: =E64 -> 0.1223946 | F87: =F64 -> 0.16695747 | G87: =G64 -> 0.21881412 | H87: =H64 -> 0.28954223 | I87: =I64 -> #ERROR!
A88: +effetto Leva finanziaria | B88: =(B87-B68)*(B30/B46) -> 0.10026175 | C88: =(C87-C68)*(C30/C46) -> 0.06024897 | D88: =(D87-D68)*(D30/D46) -> 0.12049635 | E88: =(E87-E68)*(E30/E46) -> 0.28056239 | F88: =(F87-F68)*(F30/F46) -> 0.33747742 | G88: =(G87-G68)*(G30/G46) -> 0.30140298 | H88: =(H87-H68)*(H30/H46) -> 0.50082108 | I88: =(I87-I68)*(I30/I46) -> #ERROR!
A89: +effetto Liquidità | B89: =(B72-B87)*(B31/B46) -> -0.01102346 | C89: =(C72-C87)*(C31/C46) -> -0.015201246 | D89: =(D72-D87)*(D31/D46) -> -0.027631082 | E89: =(E72-E87)*(E31/E46) -> -0.071403601 | F89: =(F72-F87)*(F31/F46) -> -0.077349132 | G89: =(G72-G87)*(G31/G46) -> -0.047997394 | H89: =(H72-H87)*(H31/H46) -> -0.1085976 | I89: =(I72-I87)*(I31/I46) -> #ERROR!
A90: +effetto Attività accessorie | B90: =(B76-B87)*(B75/B46) -> -0.0011743976 | C90: =(C76-C87)*(C75/C46) -> -0.0008951577 | D90: =(D76-D87)*(D75/D46) -> -0.00094817423 | E90: =(E76-E87)*(E75/E46) -> -0.0010951576 | F90: =(F76-F87)*(F75/F46) -> -0.00038893997 | G90: =(G76-G87)*(G75/G46) -> -0.00069207728 | H90: =(H76-H87)*(H75/H46) -> -0.0013488376 | I90: =(I76-I87)*(I75/I46) -> #ERROR!
A91: ROE lordo | B91: =SUM(B87:B90) -> 0.19794573 | C91: =SUM(C87:C90) -> 0.11954789 | D91: =SUM(D87:D90) -> 0.16252855 | E91: =SUM(E87:E90) -> 0.33045822 | F91: =SUM(F87:F90) -> 0.42669682 | G91: =SUM(G87:G90) -> 0.47152763 | H91: =SUM(H87:H90) -> 0.68041688 | I91: =SUM(I87:I90) -> #ERROR!
A93: Seconda scomposizione ROE lordo:
A94: +rendimento AON* | B94: =B64*(B14/B46) -> 0.28928034 | C94: =C64*(C14/C46) -> 0.22598653 | D94: =D64*(D14/D46) -> 0.22050876 | E94: =E64*(E14/E46) -> 0.38726623 | F94: =F64*(F14/F46) -> 0.4835607 | G94: =G64*(G14/G46) -> 0.51951394 | H94: =H64*(H14/H46) -> 0.75325343 | I94: =I64*(I14/I46) -> #ERROR!
A95: +effetto costo del debito | B95: =-B68*(B30/B46) -> -0.091654325 | C95: =-C68*(C30/C46) -> -0.10686075 | D95: =-D68*(D30/D46) -> -0.058027791 | E95: =-E68*(E30/E46) -> -0.056915299 | F95: =-F68*(F30/F46) -> -0.05693722 | G95: =-G68*(G30/G46) -> -0.049992727 | H95: =-H68*(H30/H46) -> -0.0729689 | I95: =-I68*(I30/I46) -> #ERROR!
A96: +rendimento liquidità | B96: =B72*(B31/B46) -> 0.00031971338 | C96: =C72*(C31/C46) -> 0.00042210909 | D96: =D72*(D31/D46) -> 4.7579888e-05 | E96: =E72*(E31/E46) -> 0.0001072952 | F96: =F72*(F31/F46) -> 7.3335827e-05 | G96: =G72*(G31/G46) -> 0.0020064117 | H96: =H72*(H31/H46) -> 0.00013234426 | I96: =I72*(I31/I46) -> #ERROR!
A97: +rendimento att.accessorie | B97: =B76*(B18/B46) -> 0 | C97: =C76*(C18/C46) -> 0 | D97: =D76*(D18/D46) -> 0 | E97: =E76*(E18/E46) -> 0 | F97: =F76*(F18/F46) -> 0 | G97: =G76*(G18/G46) -> 0 | H97: =H76*(H18/H46) -> 0 | I97: =I76*(I18/I46) -> #ERROR!
A98: ROE lordo | B98: =SUM(B94:B97) -> 0.19794573 | C98: =SUM(C94:C97) -> 0.11954789 | D98: =SUM(D94:D97) -> 0.16252855 | E98: =SUM(E94:E97) -> 0.33045822 | F98: =SUM(F94:F97) -> 0.42669682 | G98: =SUM(G94:G97) -> 0.47152763 | H98: =SUM(H94:H97) -> 0.68041688 | I98: =SUM(I94:I97) -> #ERROR!
A100: check ROE lordo 1: | B100: =B84-B91 -> 0 | C100: =C84-C91 -> 0 | D100: =D84-D91 -> 0 | E100: =E84-E91 -> 0 | F100: =F84-F91 -> 0 | G100: =G84-G91 -> 0 | H100: =H84-H91 -> 0 | I100: =I84-I91 -> #ERROR!
A101: check ROE lordo 2: | B101: =B84-B98 -> 0 | C101: =C84-C98 -> 0 | D101: =D84-D98 -> 0 | E101: =E84-E98 -> 0 | F101: =F84-F98 -> 0 | G101: =G84-G98 -> 0 | H101: =H84-H98 -> 0 | I101: =I84-I98 -> #ERROR!
A103: Da lordo a netto:
A104: RLA | B104: =B3 -> 1087201 | C104: =C3 -> 591071 | D104: =D3 -> 710509 | E104: =E3 -> 1204240 | F104: =F3 -> 1192771 | G104: =G3 -> 970828 | H104: =H3 -> 951134 | I104: =I3 -> 533439
A105: /CP | B105: =B46 -> 5492419.5 | C105: =C46 -> 4944219.5 | D105: =D46 -> 4371595 | E105: =E46 -> 3644152 | F105: =F46 -> 2795359.5 | G105: =G46 -> 2058899.5 | H105: =H46 -> 1397869.5 | I105: =I46 -> #ERROR!
A106: x (RLA+ris str)/RLA | B106: =(B104+B23)/B104 -> 1 | C106: =(C104+C23)/C104 -> 1 | D106: =(D104+D23)/D104 -> 1 | E106: =(E104+E23)/E104 -> 1 | F106: =(F104+F23)/F104 -> 1 | G106: =(G104+G23)/G104 -> 1 | H106: =(H104+H23)/H104 -> 1 | I106: =(I104+I23)/I104 -> 1
A107: x (RL+tax)/RL | B107: =(B3+B23+B29)/(B3+B23) -> 0.82756822 | C107: =(C3+C23+C29)/(C3+C23) -> 0.95871224 | D107: =(D3+D23+D29)/(D3+D23) -> 0.9550632 | E107: =(E3+E23+E29)/(E3+E23) -> 0.7982653 | F107: =(F3+F23+F29)/(F3+F23) -> 0.77238799 | G107: =(G3+G23+G29)/(G3+G23) -> 0.77422159 | H107: =(H3+H23+H29)/(H3+H23) -> 0.70486914 | I107: =(I3+I23+I29)/(I3+I23) -> 0.68376328
A108: '= Reddito netto/CP check | B108: =B6/B46 -> 0.1638136 | C108: =C6/C46 -> 0.11461202 | D108: =D6/D46 -> 0.15522504 | E108: =E6/E46 -> 0.26379333 | F108: =F6/F46 -> 0.3295755 | G108: =G6/G46 -> 0.36506687 | H108: =H6/H46 -> 0.47960486 | I108: =I6/I46 -> #ERROR!
A109: ROE netto | B109: =(B104/B105)*B106*B107 -> 0.1638136 | C109: =(C104/C105)*C106*C107 -> 0.11461202 | D109: =(D104/D105)*D106*D107 -> 0.15522504 | E109: =(E104/E105)*E106*E107 -> 0.26379333 | F109: =(F104/F105)*F106*F107 -> 0.3295755 | G109: =(G104/G105)*G106*G107 -> 0.36506687 | H109: =(H104/H105)*H106*H107 -> 0.47960486 | I109: =(I104/I105)*I106*I107 -> #ERROR!
A110: check ROE netto | B110: =B109-B80 -> 0 | C110: =C109-C80 -> 0 | D110: =D109-D80 -> 0 | E110: =E109-E80 -> 0 | F110: =F109-F80 -> 0 | G110: =G109-G80 -> 0 | H110: =H109-H80 -> 0 | I110: =I109-I80 -> #ERROR!
A113: INDICATORI FINANZIARI
A114: Quozienti di rotazione dell'attivo netto
...

Sheet grph
B3: Quozienti di redditività
B80: Quozienti di rotazione dell'attivo netto
B135: Quozienti di liquidità ed equilibrio fonti/impieghi
B218: Indicatori di robustezza
